Workbook
Name InverterModels: 'DropdownLists'!$A$3:$A$186
Name PanelModels: 'DropdownLists'!$B$3:$B$74
Name BatteryModels: 'DropdownLists'!$C$3:$C$26
Name RoofTypes: 'DropdownLists'!$D$3:$D$7
Name InstallationMethods: 'DropdownLists'!$E$3:$E$5
Name LightningOptions: 'DropdownLists'!$F$3:$F$6
Name EarthingSystems: 'DropdownLists'!$G$3:$G$6
Name TariffRegions: 'DropdownLists'!$H$3:$H$7
Name TariffModes: 'DropdownLists'!$I$3:$I$4

Sheet Summary
A1: Конструктор Line-Energy Solar (Line-Energy Solar Designer) | B1: v0.23.0-draft
A2: Показатель (Item) | B2: Значение (Value) | C2: Ед. изм. (Unit) | D2: Статус / примечание (Status / Note)
A3: Общая совместимость (Overall compatibility) | B3: =Compatibility!B8 | D3: PASS / FAIL / VERIFY
A4: Электрический статус PV (PV electrical status) | B4: =Results!B25 | D4: Из листа Results (From Results)
A5: Статус АКБ (Battery status) | B5: =Compatibility!B6 | D5: Из листа Compatibility (From Compatibility)
A6: Полнота datasheet (Datasheet completeness) | B6: =Compatibility!B7 | D6: Из листа Compatibility (From Compatibility)
A7: Инвертор (Inverter) | B7: =Inputs!B3 | D7: Выбранная модель (Selected model)
A8: Панель (Panel) | B8: =Inputs!B4 | D8: Выбранная модель (Selected model)
A9: АКБ (Battery) | B9: =Inputs!B9 | D9: Выбранная модель (Selected model)
A10: Панелей в строке (Panels per string) | B10: =Inputs!B7 | C10: pcs | D10: Выбранное значение (Selected value)
A11: Рекомендуемый диапазон строки (Recommended string range) | B11: =Results!B21 | C11: pcs | D11: Calculated range
A12: Общая энергия АКБ (Battery total energy) | B12: =Results!B29 | C12: kWh | D12: Номинальная энергия (Nominal energy)
A13: Тип кровли (Roof type) | B13: =Inputs!B11 | D13: Выбранная кровля (Selected roof)
A14: Всего панелей (Total panels) | B14: =Inputs!B12 | C14: pcs | D14: Ввод для крепежа (Mounting input)
A15: Ряды (Rows) | B15: =Mounting!B5 | C15: rows | D15: Расчет крепежа (Mounting calculation)
A16: Рейки (Rails) | B16: =Mounting!B13 | C16: pcs | D16: Расчет крепежа (Mounting calculation)
A17: Крайние прижимы (End clamps) | B17: =Mounting!B15 | C17: pcs | D17: Расчет крепежа (Mounting calculation)
A18: Средние прижимы (Middle clamps) | B18: =Mounting!B16 | C18: pcs | D18: Расчет крепежа (Mounting calculation)
A19: Клипсы заземления (Grounding clips) | B19: =Mounting!B18 | C19: pcs | D19: Расчет крепежа (Mounting calculation)
A20: Кабельные клипсы (Cable clips) | B20: =Mounting!B19 | C20: pcs | D20: Расчет крепежа (Mounting calculation)
A21: Позиций оборудования (Equipment list items) | B21: =COUNTA(Equipment!A2:A35) | C21: items | D21: Сформированный список оборудования (Generated equipment output)
A22: Позиций защиты (Protection items) | B22: =COUNTA(CableProtection!A2:A32) | C22: items | D22: Сформированный список защиты (Generated protection output)
A23: Сечение DC кабеля (DC cable section) | B23: =CableProtection!B15 | C23: mm2 | D23: Стартовый подбор (Starter sizing)
A24: Сечение AC кабеля (AC cable section) | B24: =CableProtection!B19 | C24: mm2 | D24: Стартовый подбор (Starter sizing)
A25: Сечение кабеля АКБ (Battery cable section) | B25: =CableProtection!B24 | C25: mm2 | D25: Стартовый подбор (Starter sizing)
A26: Рекомендация УЗИП (SPD recommendation) | B26: =CableProtection!B28 | D26: Стартовый выбор защиты (Starter protection selection)
A27: Система заземления (Earthing system) | B27: =CableProtection!B29 | D27: Выбранная система заземления AC (Selected AC earthing system)
A28: Коэффициент снижения нагрузки кабеля (Cable derating factor) | B28: =CableProtection!B30 | C28: factor | D28: Группировка x температурные коэффициенты (Grouping x ambient factors)
A29: Массовые сценарии (Bulk scenarios) | B29: =COUNTA(BulkCompatibility!A2:A100) | C29: rows | D29: Mass compatibility table
A30: Массовые PASS (Bulk PASS) | B30: =COUNTIF(BulkCompatibility!L2:L100,"PASS") | C30: rows | D30: Bulk compatibility count
A31: Массовые FAIL (Bulk FAIL) | B31: =COUNTIF(BulkCompatibility!L2:L100,"FAIL") | C31: rows | D31: Bulk compatibility count
A32: Массовые VERIFY (Bulk VERIFY) | B32: =COUNTIF(BulkCompatibility!L2:L100,"VERIFY") | C32: rows | D32: Bulk compatibility count
A33: Регион (Region) | B33: =Economics!B2 | D33: Economics input
A34: Годовая выработка (Annual generation) | B34: =Economics!B8 | C34: kWh/year | D34: Оценка региональной выработки (Regional yield estimate)
A35: Годовая экономия (Annual savings) | B35: =Economics!B12 | C35: RUB/year | D35: Собственное потребление плюс экспорт (Self-consumption plus export)
A36: Простая окупаемость (Simple payback) | B36: =Economics!B13 | C36: years | D36: Стоимость системы / годовая экономия (Installed cost / annual savings)
A37: Статус источника тарифа (Tariff source status) | B37: =Economics!B15 | D37: Нужно проверить (Must be verified)
A38: Потребление в месяц (Monthly consumption) | B38: =Inputs!B29 | C38: kWh/month | D38: Ввод клиента (Customer input)
A39: Целевое покрытие (Target coverage) | B39: =Inputs!B30 | C39: % | D39: Цель подбора варианта (Option sizing target)
A40: Рекомендуемая стандартная мощность (Recommended standard size) | B40: =SystemOptions!H3 | C40: kWp | D40: Лист SystemOptions (SystemOptions)
A41: Годовая выработка стандартного варианта (Standard option annual generation) | B41: =SystemOptions!K3 | C41: kWh/year | D41: Лист SystemOptions (SystemOptions)
A42: Окупаемость стандартного варианта день-ночь (Standard option payback day-night) | B42: =SystemOptions!R3 | C42: years | D42: Лист SystemOptions (SystemOptions)
A43: Выработка в лучший месяц (Best month generation) | B43: =MAX(MonthlyGeneration!B2:B13) | C43: kWh/month | D43: MonthlyGeneration
A44: Выработка в худший месяц (Worst month generation) | B44: =MIN(MonthlyGeneration!B2:B13) | C44: kWh/month | D44: MonthlyGeneration
A45: Ценность собственного потребления по месяцам (Monthly self-consumption value) | B45: =SUM(MonthlyGeneration!E2:E13) | C45: RUB/year | D45: MonthlyGeneration
A46: Ценность экспорта по месяцам (Monthly export value) | B46: =SUM(MonthlyGeneration!F2:F13) | C46: RUB/year | D46: MonthlyGeneration

Sheet Inputs
A1: Калькулятор Line-Energy Solar (Line-Energy Solar Calculator) | B1: v0.23.0-draft
A2: Ввод (Input) | B2: Значение (Value) | C2: Ед. изм. (Unit) | D2: Примечания (Notes)
A3: Модель инвертора (Inverter model) | B3: SUN-8K-SG01LP1-EU | D3: Выберите из списка (Choose from dropdown)
A4: Модель панели (Panel model) | B4: JKM575N-72HL4-V | D4: Выберите из списка (Choose from dropdown)
A5: Минимальная температура воздуха (Minimum ambient temperature) | B5: -10 | C5: C | D5: Для проверки Voc на холоде (Used for cold Voc check)
A6: Максимальная температура ячейки (Maximum cell temperature) | B6: 70 | C6: C | D6: Для проверки Vmp на нагреве (Used for hot Vmp check)
A7: Панелей в строке (Panels per string) | B7: 8 | C7: pcs | D7: Модули последовательно в одной строке (Series modules in one string)
A8: Строк на MPPT (Strings per MPPT) | B8: 1 | C8: pcs | D8: Параллельные строки на один трекер (Parallel strings on one tracker)
A9: Модель АКБ (Battery model) | B9: US5000 | D9: Выберите из списка (Choose from dropdown)
A10: Количество АКБ (Battery quantity) | B10: 2 | C10: pcs | D10: Для расчета общей емкости АКБ (Used for total battery capacity)
A11: Тип кровли (Roof type) | B11: Metal tile | D11: Выберите из списка (Choose from dropdown)
A12: Всего панелей (Total panels) | B12: 16 | C12: pcs | D12: Для расчета количества крепежа (Used for mounting quantity calculation)
A13: Панелей в ряду (Panels per row) | B13: 8 | C13: pcs | D13: Для расчета рядов и прижимов (Used for row and clamp calculation)
A14: Длина рейки со склада (Rail stock length) | B14: 4.2 | C14: m | D14: Для оценки соединителей рейки (Used for rail connector estimate)
A15: Длина рейки на панель (Rail length per panel) | B15: 1.15 | C15: m | D15: Стартовое допущение; уточнить по ориентации панели (Starter assumption; adjust by panel orientation)
A16: Запас крепежа (Mounting reserve) | B16: 10 | C16: % | D16: Дополнительный запас количества (Extra quantity reserve)
A17: Длина DC кабеля (DC cable route length) | B17: 30 | C17: m | D17: Оценка длины трассы в одну сторону (One-way route length estimate)
A18: Длина AC кабеля (AC cable route length) | B18: 20 | C18: m | D18: Оценка длины трассы в одну сторону (One-way route length estimate)
A19: Длина кабеля заземления (Grounding cable route length) | B19: 25 | C19: m | D19: Grounding route length estimate
A20: Способ прокладки (Installation method) | B20: Open air | D20: Для примечаний по снижению нагрузки кабеля (Used for cable derating notes)
A21: Коэффициент группировки кабелей (Cable grouping derating) | B21: 1 | C21: factor | D21: Стартовый коэффициент; уточнить по местным нормам (Starter factor; adjust by local rules)
A22: Коэффициент температуры окружающей среды (Ambient temperature derating) | B22: 1 | C22: factor | D22: Стартовый коэффициент; уточнить по местным нормам (Starter factor; adjust by local rules)
A23: Система молниезащиты (Lightning protection system) | B23: No external LPS | D23: Для рекомендации типа УЗИП (Used for SPD type suggestion)
A24: Система заземления AC (AC earthing system) | B24: TN-S | D24: Для чек-листа заземления (Used for earthing checklist)
A25: Регион / тарифная зона (Region / tariff zone) | B25: Moscow starter | D25: Выберите из базы тарифов (Choose from tariff database)
A26: Доля собственного потребления (Self-consumption share) | B26: 70 | C26: % | D26: Доля выработки, потребляемая на объекте (Share of generation consumed on site)
A27: Стоимость установленной системы (Installed system cost) | B27: 800000 | C27: RUB | D27: Для оценки простой окупаемости (Used for simple payback estimate)
A28: Статус источника тарифа (Tariff source status) | B28: VERIFY | D28: Тарифы нужно сверить по поставщику и дате (Tariffs must be checked for exact supplier/date)
A29: Потребление в месяц (Monthly consumption) | B29: 1000 | C29: kWh/month | D29: Месячное потребление клиента (Customer monthly electricity consumption)
A30: Целевое покрытие (Target coverage) | B30: 70 | C30: % | D30: Рекомендуемые варианты покрывают эту долю годового потребления (Recommended options cover this share of annual consumption)
A31: Режим тарифа (Tariff mode) | B31: Single-rate | D31: Сравнение единого тарифа и день-ночь (Single-rate or Day-night comparison)
A32: Доля дневного потребления (Day consumption share) | B32: 65 | C32: % | D32: Для сравнения тарифа день-ночь (Used for day-night tariff comparison)
A33: Дневной тариф (Day tariff) | B33: 9.8 | C33: RUB/kWh | D33: Стартовый дневной тариф; сверить поставщика/дату (Starter day tariff; verify supplier/date)
A34: Ночной тариф (Night tariff) | B34: 3.5 | C34: RUB/kWh | D34: Стартовый ночной тариф; сверить поставщика/дату (Starter night tariff; verify supplier/date)
A35: Примечание по расчету (Design note) | B35: Только стартовый расчет (Starter calculation only) | D35: Проверить datasheet и инструкции по крепежу перед коммерческим применением (Verify datasheets and mounting manuals before commercial use)

Sheet Results
A1: Результат (Result) | B1: Значение (Value) | C1: Ед. изм. (Unit) | D1: Формула / смысл (Formula / meaning)
A2: Модель инвертора (Inverter model) | B2: =Inputs!B3 | D2: Из листа Inputs (From Inputs)
A3: Модель панели (Panel model) | B3: =Inputs!B4 | D3: Из листа Inputs (From Inputs)
A4: Панелей в строке (Panels per string) | B4: =Inputs!B7 | C4: pcs | D4: Из листа Inputs (From Inputs)
A5: Строк на MPPT (Strings per MPPT) | B5: =Inputs!B8 | C5: pcs | D5: Из листа Inputs (From Inputs)
A6: Max PV voltage | B6: =INDEX(Inverters!G:G,MATCH(B2,Inverters!C:C,0)) | C6: V | D6: Inverter absolute PV voltage limit
A7: MPPT min voltage | B7: =INDEX(Inverters!I:I,MATCH(B2,Inverters!C:C,0)) | C7: V | D7: Inverter lower MPPT voltage
A8: MPPT max voltage | B8: =INDEX(Inverters!J:J,MATCH(B2,Inverters!C:C,0)) | C8: V | D8: Inverter upper MPPT voltage
A9: Max input current per MPPT | B9: =INDEX(Inverters!M:M,MATCH(B2,Inverters!C:C,0)) | C9: A | D9: Inverter current limit
A10: Panel Voc STC | B10: =INDEX(Panels!G:G,MATCH(B3,Panels!C:C,0)) | C10: V | D10: Open-circuit voltage at STC
A11: Panel Vmp STC | B11: =INDEX(Panels!E:E,MATCH(B3,Panels!C:C,0)) | C11: V | D11: Voltage at maximum power at STC
A12: Panel Imp STC | B12: =INDEX(Panels!F:F,MATCH(B3,Panels!C:C,0)) | C12: A | D12: Current at maximum power at STC
A13: Panel voltage temperature coefficient | B13: =INDEX(Panels!J:J,MATCH(B3,Panels!C:C,0)) | C13: %/C | D13: Preliminary voltage correction
A14: Cold Voc per panel | B14: =B10*(1+(B13/100)*(Inputs!B5-25)) | C14: V | D14: Voc at minimum temperature
A15: Hot Vmp per panel | B15: =B11*(1+(B13/100)*(Inputs!B6-25)) | C15: V | D15: Vmp at maximum cell temperature
A16: Cold string Voc | B16: =B14*B4 | C16: V | D16: Cold Voc per panel x panels per string
A17: Hot string Vmp | B17: =B15*B4 | C17: V | D17: Hot Vmp per panel x panels per string
A18: Minimum panels per string by MPPT | B18: =ROUNDUP(B7/B15,0) | C18: pcs | D18: Ceiling of MPPT min / hot Vmp per panel
A19: Maximum panels per string by MPPT | B19: =ROUNDDOWN(B8/B15,0) | C19: pcs | D19: Floor of MPPT max / hot Vmp per panel
A20: Maximum panels per string by PV voltage | B20: =ROUNDDOWN(B6/B14,0) | C20: pcs | D20: Floor of max PV voltage / cold Voc per panel
A21: Recommended panels per string range | B21: =B18&" - "&MIN(B19,B20) | C21: pcs | D21: Minimum to safest maximum
A22: MPPT operating check | B22: =IF(AND(B17>=B7,B17<=B8),"PASS","FAIL") | D22: Hot Vmp must stay inside MPPT window
A23: Max voltage check | B23: =IF(B16<B6,"PASS","FAIL") | D23: Cold Voc must stay below max PV voltage
A24: Current check | B24: =IF(B12*B5<=B9,"PASS","FAIL") | D24: Parallel string current must stay below MPPT current
A25: Overall preliminary status | B25: =IF(AND(B22="PASS",B23="PASS",B24="PASS"),"PASS","FAIL") | D25: All checks must pass
A26: Модель АКБ (Battery model) | B26: =Inputs!B9 | D26: Из листа Inputs (From Inputs)
A27: Количество АКБ (Battery quantity) | B27: =Inputs!B10 | C27: pcs | D27: Из листа Inputs (From Inputs)
A28: Battery nominal energy | B28: =INDEX(Batteries!E:E,MATCH(B26,Batteries!C:C,0)) | C28: kWh | D28: Из базы Batteries (From Batteries database)
A29: Total nominal battery energy | B29: =B27*B28 | C29: kWh | D29: Battery energy x quantity
A30: Battery compatibility note | B30: =INDEX(Batteries!M:M,MATCH(B26,Batteries!C:C,0)) | D30: Из базы Batteries (From Batteries database)

Sheet Inverters
A1: brand | B1: series | C1: model | D1: phase | E1: nominal_ac_power_w | F1: max_pv_input_power_w | G1: max_pv_voltage_v | H1: startup_voltage_v | I1: mppt_voltage_min_v | J1: mppt_voltage_max_v | K1: mppt_count | L1: strings_per_mppt | M1: max_input_current_per_mppt_a | N1: max_short_circuit_current_per_mppt_a | O1: battery_nominal_voltage_v | P1: battery_voltage_range_v | Q1: data_status | R1: notes
A2: Anenji | B2: Hybrid | C2: ANJ-3.2KW-24V | D2: single-phase | E2: 3200 | O2: 24 | Q2: model_only_needs_datasheet | R2: Hybrid inverter model candidate; datasheet parameters pending.
A3: Anenji | B3: Hybrid | C3: ANJ-3.6KW-24V | D3: single-phase | E3: 3600 | O3: 24 | Q3: model_only_needs_datasheet | R3: Hybrid inverter model candidate; datasheet parameters pending.
A4: Anenji | B4: Hybrid | C4: ANJ-4.2KW-24V | D4: single-phase | E4: 4200 | O4: 24 | Q4: model_only_needs_datasheet | R4: Hybrid inverter model candidate; datasheet parameters pending.
A5: Anenji | B5: Hybrid | C5: ANJ-6.2KW-48V | D5: single-phase | E5: 6200 | O5: 48 | Q5: model_only_needs_datasheet | R5: Hybrid inverter model candidate; datasheet parameters pending.
A6: Anenji | B6: Hybrid | C6: ANJ-8.2KW-48V | D6: single-phase | E6: 8200 | O6: 48 | Q6: model_only_needs_datasheet | R6: Hybrid inverter model candidate; datasheet parameters pending.
A7: Anenji | B7: Hybrid | C7: ANJ-10.2KW-48V | D7: single-phase | E7: 10200 | O7: 48 | Q7: model_only_needs_datasheet | R7: Hybrid inverter model candidate; datasheet parameters pending.
A8: Anenji | B8: Hybrid | C8: ANJ-11KW-48V | D8: single-phase | E8: 11000 | O8: 48 | Q8: model_only_needs_datasheet | R8: Hybrid inverter model candidate; datasheet parameters pending.
A9: Anenji | B9: Hybrid | C9: ANJ-12KW-48V | D9: single-phase | E9: 12000 | O9: 48 | Q9: model_only_needs_datasheet | R9: Hybrid inverter model candidate; datasheet parameters pending.
A10: Deye | B10: Hybrid LV 24V | C10: SUN-3K-SG04LP1-24-EU | D10: single-phase | E10: 3000 | O10: 24 | Q10: model_only_needs_datasheet | R10: Model list provided by user; datasheet parameters pending.
A11: Deye | B11: Hybrid LV | C11: SUN-3K-SG04LP1-EU | D11: single-phase | E11: 3000 | O11: 48 | Q11: model_only_needs_datasheet | R11: Model list provided by user; datasheet parameters pending.
A12: Deye | B12: Hybrid LV | C12: SUN-3.6K-SG05LP1-EU-AM2-P | D12: single-phase | E12: 3600 | F12: 7200 | G12: 500 | H12: 125 | I12: 150 | J12: 425 | K12: 2 | L12: 2+2 | M12: 32 | N12: 48 | O12: 48 | P12: 40-60 | Q12: datasheet_local_pdf_verified | R12: Local PDF: SUN-_3.6-10_K-SG05LP1-EU-AM2-P_RU.pdf
A13: Deye | B13: Hybrid LV | C13: SUN-5K-SG05LP1-EU-AM2-P | D13: single-phase | E13: 5000 | F13: 10000 | G13: 500 | H13: 125 | I13: 150 | J13: 425 | K13: 2 | L13: 2+2 | M13: 32 | N13: 48 | O13: 48 | P13: 40-60 | Q13: datasheet_local_pdf_verified | R13: Local PDF: SUN-_3.6-10_K-SG05LP1-EU-AM2-P_RU.pdf
A14: Deye | B14: Hybrid LV | C14: SUN-6K-SG05LP1-EU-AM2-P | D14: single-phase | E14: 6000 | F14: 12000 | G14: 500 | H14: 125 | I14: 150 | J14: 425 | K14: 2 | L14: 2+2 | M14: 32 | N14: 48 | O14: 48 | P14: 40-60 | Q14: datasheet_local_pdf_verified | R14: Local PDF: SUN-_3.6-10_K-SG05LP1-EU-AM2-P_RU.pdf
A15: Deye | B15: Hybrid LV | C15: SUN-8K-SG05LP1-EU-AM2-P | D15: single-phase | E15: 8000 | F15: 16000 | G15: 500 | H15: 125 | I15: 150 | J15: 425 | K15: 2 | L15: 2+2 | M15: 32 | N15: 48 | O15: 48 | P15: 40-60 | Q15: datasheet_local_pdf_verified | R15: Local PDF: SUN-_3.6-10_K-SG05LP1-EU-AM2-P_RU.pdf
A16: Deye | B16: Hybrid LV | C16: SUN-10K-SG02LP1-EU-AM3-P | D16: single-phase | E16: 10000 | F16: 20000 | G16: 500 | H16: 125 | I16: 150 | J16: 425 | K16: 3 | L16: 2+2+2 | M16: 32 | N16: 60 | O16: 48 | P16: 40-60 | Q16: datasheet_local_pdf_verified | R16: Local PDF: SUN-_7.6-12_K-SG02LP1-EU-AM2-P_RU.pdf
A17: Deye | B17: Hybrid LV | C17: SUN-12K-SG02LP1-EU-AM3-P | D17: single-phase | E17: 12000 | F17: 24000 | G17: 500 | H17: 125 | I17: 150 | J17: 425 | K17: 3 | L17: 2+2+2 | M17: 32 | N17: 60 | O17: 48 | P17: 40-60 | Q17: datasheet_local_pdf_verified | R17: Local PDF: SUN-_7.6-12_K-SG02LP1-EU-AM2-P_RU.pdf
A18: Deye | B18: Hybrid LV | C18: SUN-14K-SG01LP1-EU-AM3-P | D18: single-phase | E18: 14000 | F18: 28000 | G18: 500 | H18: 125 | I18: 150 | J18: 425 | K18: 3 | L18: 2+2+2 | M18: 36 | N18: 54 | O18: 48 | P18: 40-60 | Q18: datasheet_local_pdf_verified | R18: Local PDF: SUN-_12-18_K-SG01LP1-EU-AM3-P_RU.pdf
A19: Deye | B19: Hybrid LV | C19: SUN-16K-SG01LP1-EU-AM3-P | D19: single-phase | E19: 16000 | F19: 32000 | G19: 500 | H19: 125 | I19: 150 | J19: 425 | K19: 3 | L19: 2+2+2 | M19: 36 | N19: 54 | O19: 48 | P19: 40-60 | Q19: datasheet_local_pdf_verified | R19: Local PDF: SUN-_12-18_K-SG01LP1-EU-AM3-P_RU.pdf
A20: Deye | B20: Hybrid LV | C20: SUN-18K-SG01LP1-EU-AM3-P | D20: single-phase | E20: 18000 | F20: 36000 | G20: 500 | H20: 125 | I20: 150 | J20: 425 | K20: 3 | L20: 2+2+2 | M20: 36 | N20: 54 | O20: 48 | P20: 40-60 | Q20: datasheet_local_pdf_verified | R20: Local PDF: SUN-_12-18_K-SG01LP1-EU-AM3-P_RU.pdf
A21: Deye | B21: Hybrid LV 3P | C21: SUN-5K-SG05LP3-EU-SM2 | D21: three-phase | E21: 5000 | F21: 10000 | G21: 800 | H21: 160 | I21: 200 | J21: 650 | K21: 2 | L21: 1+1 | M21: 20 | N21: 30 | O21: 48 | P21: 40-60 | Q21: datasheet_local_pdf_verified | R21: Local PDF: SUN-_3-12_K-SG05LP3-EU-SM2_RU.pdf
A22: Deye | B22: Hybrid LV 3P | C22: SUN-6K-SG05LP3-EU-SM2 | D22: three-phase | E22: 6000 | F22: 12000 | G22: 800 | H22: 160 | I22: 200 | J22: 650 | K22: 2 | L22: 1+1 | M22: 20 | N22: 30 | O22: 48 | P22: 40-60 | Q22: datasheet_local_pdf_verified | R22: Local PDF: SUN-_3-12_K-SG05LP3-EU-SM2_RU.pdf
A23: Deye | B23: Hybrid LV 3P | C23: SUN-8K-SG05LP3-EU-SM2 | D23: three-phase | E23: 8000 | F23: 16000 | G23: 800 | H23: 160 | I23: 200 | J23: 650 | K23: 2 | L23: 2+2 | M23: 26 | N23: 39 | O23: 48 | P23: 40-60 | Q23: datasheet_local_pdf_verified | R23: Local PDF: SUN-_3-12_K-SG05LP3-EU-SM2_RU.pdf
... A30: Deye | B30: Hybrid LV 3P | C30: SUN-20K-SG05LP3-EU-SM2 | D30: three-phase | E30: 20000 | F30: 40000 | G30: 800 | H30: 160 | I30: 160 | J30: 650 | K30: 2 | L30: 2+2 | M30: 36 | N30: 54 | O30: 48 | P30: 40-60 | Q30: datasheet_local_pdf_verified | R30: Local PDF: SUN-_14-20_K-SG05LP3-EU-SM2_RU.pdf
A31: Deye | B31: Hybrid HV 3P | C31: SUN-10K-SG01HP3-EU-AM2 | D31: three-phase | E31: 10000 | F31: 20000 | G31: 1000 | H31: 180 | I31: 150 | J31: 850 | K31: 2 | L31: 1+1 | M31: 20 | N31: 30 | P31: 160-700 | Q31: datasheet_local_pdf_verified | R31: Local PDF: SUN-_5-25_K-SG01HP3-EU-AM2_RU.pdf
A32: Deye | B32: Hybrid HV 3P | C32: SUN-12K-SG01HP3-EU-AM2 | D32: three-phase | E32: 12000 | F32: 24000 | G32: 1000 | H32: 180 | I32: 150 | J32: 850 | K32: 2 | L32: 1+1 | M32: 20 | N32: 30 | P32: 160-700 | Q32: datasheet_local_pdf_verified | R32: Local PDF: SUN-_5-25_K-SG01HP3-EU-AM2_RU.pdf
A33: Deye | B33: Hybrid HV 3P | C33: SUN-15K-SG01HP3-EU-AM2 | D33: three-phase | E33: 15000 | F33: 30000 | G33: 1000 | H33: 180 | I33: 150 | J33: 850 | K33: 2 | L33: 2+2 | M33: 26 | N33: 39 | P33: 160-700 | Q33: datasheet_local_pdf_verified | R33: Local PDF: SUN-_5-25_K-SG01HP3-EU-AM2_RU.pdf
A34: Deye | B34: Hybrid HV 3P | C34: SUN-20K-SG01HP3-EU-AM2 | D34: three-phase | E34: 20000 | F34: 40000 | G34: 1000 | H34: 180 | I34: 150 | J34: 850 | K34: 2 | L34: 2+2 | M34: 26 | N34: 39 | P34: 160-700 | Q34: datasheet_local_pdf_verified | R34: Local PDF: SUN-_5-25_K-SG01HP3-EU-AM2_RU.pdf
A35: Deye | B35: Hybrid HV 3P | C35: SUN-25K-SG01HP3-EU-AM2 | D35: three-phase | E35: 25000 | F35: 50000 | G35: 1000 | H35: 180 | I35: 150 | J35: 850 | K35: 2 | L35: 2+1 | M35: 26 | N35: 39 | P35: 160-700 | Q35: datasheet_local_pdf_verified | R35: Local PDF: SUN-_5-25_K-SG01HP3-EU-AM2_RU.pdf
A36: Deye | B36: Hybrid HV 3P | C36: SUN-30K-SG02HP3-EU-AM3 | D36: three-phase | E36: 30000 | F36: 60000 | G36: 1000 | H36: 180 | I36: 150 | J36: 850 | K36: 3 | L36: 2+2+2 | M36: 36 | N36: 54 | P36: 160-700 | Q36: datasheet_local_pdf_verified | R36: Local PDF: SUN-_25-30_K-SG02HP3-EU-AM3_RU.pdf
A37: Deye | B37: Hybrid HV 3P | C37: SUN-40K-SG01HP3-EU-BM4 | D37: three-phase | E37: 40000 | F37: 80000 | G37: 1000 | H37: 180 | I37: 150 | J37: 850 | K37: 3 | L37: 2+2+2 | M37: 36 | N37: 55 | P37: 160-800 | Q37: datasheet_local_pdf_verified | R37: Local PDF: SUN-_29.9-50_K-SG01HP3-EU-BM4_RU.pdf
A38: Deye | B38: Hybrid HV 3P | C38: SUN-50K-SG01HP3-EU-BM4 | D38: three-phase | E38: 50000 | F38: 100000 | G38: 1000 | H38: 180 | I38: 150 | J38: 850 | K38: 4 | L38: 2+2+2+2 | M38: 36 | N38: 55 | P38: 160-800 | Q38: datasheet_local_pdf_verified | R38: Local PDF: SUN-_29.9-50_K-SG01HP3-EU-BM4_RU.pdf
A39: Deye | B39: Hybrid HV 3P | C39: SUN-60K-SG02HP3-EU-EM6 | D39: three-phase | E39: 60000 | F39: 120000 | G39: 1000 | H39: 180 | I39: 150 | J39: 850 | K39: 6 | L39: 2+2+2+2+2+2 | M39: 36 | N39: 54 | P39: 160-1000 | Q39: datasheet_local_pdf_verified | R39: Local PDF: SUN-_60-80_K-SG02HP3-EU-EM6_RU.pdf
A40: Deye | B40: Hybrid HV 3P | C40: SUN-70K-SG02HP3-EU-EM6 | D40: three-phase | E40: 70000 | F40: 140000 | G40: 1000 | H40: 180 | I40: 150 | J40: 850 | K40: 6 | L40: 2+2+2+2+2+2 | M40: 36 | N40: 54 | P40: 160-1000 | Q40: datasheet_local_pdf_verified | R40: Local PDF: SUN-_60-80_K-SG02HP3-EU-EM6_RU.pdf
A41: Deye | B41: Hybrid HV 3P | C41: SUN-75K-SG02HP3-EU-EM6 | D41: three-phase | E41: 75000 | F41: 150000 | G41: 1000 | H41: 180 | I41: 150 | J41: 850 | K41: 6 | L41: 2+2+2+2+2+2 | M41: 36 | N41: 54 | P41: 160-1000 | Q41: datasheet_local_pdf_verified | R41: Local PDF: SUN-_60-80_K-SG02HP3-EU-EM6_RU.pdf
A42: Deye | B42: Hybrid HV 3P | C42: SUN-80K-SG02HP3-EU-EM6 | D42: three-phase | E42: 80000 | F42: 160000 | G42: 1000 | H42: 180 | I42: 150 | J42: 850 | K42: 6 | L42: 2+2+2+2+2+2 | M42: 36 | N42: 54 | P42: 160-1000 | Q42: datasheet_local_pdf_verified | R42: Local PDF: SUN-_60-80_K-SG02HP3-EU-EM6_RU.pdf
... A44: Deye | B44: Hybrid HV 3P | C44: SUN-125K-SG02HP3-EU-GM10 | D44: three-phase | E44: 125000 | F44: 250000 | G44: 1000 | H44: 180 | I44: 150 | J44: 850 | K44: 10 | L44: 2+2+2+2+2+2+2+2+2+2 | M44: 42 | N44: 63 | P44: 160-1000 | Q44: datasheet_local_pdf_verified | R44: Local PDF: SUN-_100-125_K-SG02HP3-EU-GM10_RU.pdf
A45: Deye | B45: Grid 1P | C45: SUN-1K-G04P1-EU-AM1 | D45: single-phase | E45: 1000 | Q45: model_only_needs_datasheet | R45: Model list provided by user; datasheet parameters pending.
A46: Deye | B46: Grid 1P | C46: SUN-1.5K-G04P1-EU-AM1 | D46: single-phase | E46: 1500 | Q46: model_only_needs_datasheet | R46: Model list provided by user; datasheet parameters pending.
A47: Deye | B47: Grid 1P | C47: SUN-2K-G04P1-EU-AM1 | D47: single-phase | E47: 2000 | Q47: model_only_needs_datasheet | R47: Model list provided by user; datasheet parameters pending.
A48: Deye | B48: Grid 1P | C48: SUN-3K-G04P1-EU-AM1 | D48: single-phase | E48: 3000 | Q48: model_only_needs_datasheet | R48: Model list provided by user; datasheet parameters pending.
A49: Deye | B49: Grid 1P | C49: SUN-3.6K-G04P1-EU-AM1 | D49: single-phase | E49: 3600 | Q49: model_only_needs_datasheet | R49: Model list provided by user; datasheet parameters pending.
A50: Deye | B50: Grid 1P | C50: SUN-4K-G04P1-EU-AM1 | D50: single-phase | E50: 4000 | Q50: model_only_needs_datasheet | R50: Model list provided by user; datasheet parameters pending.
A51: Deye | B51: Grid 1P | C51: SUN-4K-G05P1-EU-AM2 | D51: single-phase | E51: 4000 | F51: 6000 | G51: 550 | H51: 80 | I51: 70 | J51: 500 | K51: 2 | L51: 1+1 | M51: 18 | N51: 27 | Q51: datasheet_local_pdf_verified | R51: Local PDF: SUN-_3.6-6.2_K-G05P1-EU-AM2_RU.pdf
A52: Deye | B52: Grid 1P | C52: SUN-5K-G05P1-EU-AM2 | D52: single-phase | E52: 5000 | F52: 7500 | G52: 550 | H52: 80 | I52: 70 | J52: 500 | K52: 2 | L52: 1+1 | M52: 18 | N52: 27 | Q52: datasheet_local_pdf_verified | R52: Local PDF: SUN-_3.6-6.2_K-G05P1-EU-AM2_RU.pdf
A53: Deye | B53: Grid 1P | C53: SUN-6K-G05P1-EU-AM2 | D53: single-phase | E53: 6000 | F53: 9000 | G53: 550 | H53: 80 | I53: 70 | J53: 500 | K53: 2 | L53: 1+1 | M53: 18 | N53: 27 | Q53: datasheet_local_pdf_verified | R53: Local PDF: SUN-_3.6-6.2_K-G05P1-EU-AM2_RU.pdf
A54: Deye | B54: Grid 1P | C54: SUN-7K-G02P1-EU-AM2 | D54: single-phase | E54: 7000 | F54: 9100 | G54: 550 | H54: 80 | I54: 70 | J54: 500 | K54: 2 | L54: 1+2 | M54: 26 | N54: 39 | Q54: datasheet_local_pdf_verified | R54: Local PDF: SUN-_7-8_K-G02P1-EU-AM2_RU.pdf
A55: Deye | B55: Grid 1P | C55: SUN-7.5K-G02P1-EU-AM2 | D55: single-phase | E55: 7500 | F55: 9800 | G55: 550 | H55: 80 | I55: 70 | J55: 500 | K55: 2 | L55: 1+2 | M55: 26 | N55: 39 | Q55: datasheet_local_pdf_verified | R55: Local PDF: SUN-_7-8_K-G02P1-EU-AM2_RU.pdf
A56: Deye | B56: Grid 1P | C56: SUN-8K-G02P1-EU-AM2 | D56: single-phase | E56: 8000 | F56: 10400 | G56: 550 | H56: 80 | I56: 70 | J56: 500 | K56: 2 | L56: 1+2 | M56: 26 | N56: 39 | Q56: datasheet_local_pdf_verified | R56: Local PDF: SUN-_7-8_K-G02P1-EU-AM2_RU.pdf
A57: Deye | B57: Grid 1P | C57: SUN-9K-G02P1-EU-AM2 | D57: single-phase | E57: 9000 | F57: 13500 | G57: 550 | H57: 80 | I57: 70 | J57: 500 | K57: 2 | L57: 2+2 | M57: 26 | N57: 39 | Q57: datasheet_local_pdf_verified | R57: Local PDF: SUN-_9-10.5_K-G02P1-EU-AM2_RU.pdf
A58: Deye | B58: Grid 1P | C58: SUN-10K-G02P1-EU-AM2 | D58: single-phase | E58: 10000 | F58: 15000 | G58: 550 | H58: 80 | I58: 70 | J58: 500 | K58: 2 | L58: 2+2 | M58: 26 | N58: 39 | Q58: datasheet_local_pdf_verified | R58: Local PDF: SUN-_9-10.5_K-G02P1-EU-AM2_RU.pdf
A59: Deye | B59: Grid 3P | C59: SUN-4K-G06P3-EU-BM2-P1 | D59: three-phase | E59: 4000 | F59: 6000 | G59: 1100 | H59: 140 | I59: 120 | J59: 1000 | K59: 2 | L59: 1+1 | M59: 13 | N59: 19.5 | Q59: datasheet_local_pdf_suffix_review | R59: Local PDF: SUN-_3-15_K-G06P3-EU-BM2_RU.pdf; catalog model suffix is BM2-P1, source PDF suffix is BM2.
A60: Deye | B60: Grid 3P | C60: SUN-5K-G06P3-EU-BM2-P1 | D60: three-phase | E60: 5000 | F60: 7500 | G60: 1100 | H60: 140 | I60: 120 | J60: 1000 | K60: 2 | L60: 1+1 | M60: 13 | N60: 19.5 | Q60: datasheet_local_pdf_suffix_review | R60: Local PDF: SUN-_3-15_K-G06P3-EU-BM2_RU.pdf; catalog model suffix is BM2-P1, source PDF suffix is BM2.
A61: Deye | B61: Grid 3P | C61: SUN-6K-G06P3-EU-BM2-P1 | D61: three-phase | E61: 6000 | F61: 9000 | G61: 1100 | H61: 140 | I61: 120 | J61: 1000 | K61: 2 | L61: 1+1 | M61: 13 | N61: 19.5 | Q61: datasheet_local_pdf_suffix_review | R61: Local PDF: SUN-_3-15_K-G06P3-EU-BM2_RU.pdf; catalog model suffix is BM2-P1, source PDF suffix is BM2.
A62: Deye | B62: Grid 3P | C62: SUN-7K-G06P3-EU-BM2-P1 | D62: three-phase | E62: 7000 | F62: 10500 | G62: 1100 | H62: 140 | I62: 120 | J62: 1000 | K62: 2 | L62: 1+1 | M62: 13 | N62: 19.5 | Q62: datasheet_local_pdf_suffix_review | R62: Local PDF: SUN-_3-15_K-G06P3-EU-BM2_RU.pdf; catalog model suffix is BM2-P1, source PDF suffix is BM2.
... A80: Deye | B80: Grid 3P | C80: SUN-80K-G04P3-EU-AM4 | D80: three-phase | E80: 80000 | F80: 120000 | G80: 1100 | H80: 250 | I80: 200 | J80: 1000 | K80: 4 | L80: 4+4+4+4 | M80: 40 | N80: 60 | Q80: datasheet_local_pdf_verified | R80: Local PDF: SUN-_60-80_K-G04P3-EU-AM4_RU.pdf
A81: Deye | B81: Grid 3P | C81: SUN-100K-G03 | D81: three-phase | E81: 100000 | Q81: model_only_needs_datasheet | R81: Model list provided by user; datasheet parameters pending.
A82: Deye | B82: Grid 3P | C82: SUN-110K-G03 | D82: three-phase | E82: 110000 | Q82: model_only_needs_datasheet | R82: Model list provided by user; datasheet parameters pending.
A83: Deye | B83: Grid 3P | C83: SUN-120K-G01P3-EU-AM8 | D83: three-phase | E83: 120000 | Q83: model_only_needs_datasheet | R83: Model list provided by user; datasheet parameters pending.
A84: Deye | B84: Grid 3P | C84: SUN-125K-G01P3-EU-AM8 | D84: three-phase | E84: 125000 | Q84: model_only_needs_datasheet | R84: Model list provided by user; datasheet parameters pending.
A85: Deye | B85: Grid 3P | C85: SUN-130K-G01P3-EU-AM8 | D85: three-phase | E85: 130000 | Q85: model_only_needs_datasheet | R85: Model list provided by user; datasheet parameters pending.
A86: Deye | B86: Grid 3P | C86: SUN-135K-G01P3-EU-AM8 | D86: three-phase | E86: 135000 | Q86: model_only_needs_datasheet | R86: Model list provided by user; datasheet parameters pending.
A87: Deye | B87: Grid 3P | C87: SUN-136K-G01P3-EU-AM8 | D87: three-phase | E87: 136000 | Q87: model_only_needs_datasheet | R87: Model list provided by user; datasheet parameters pending.
A88: Deye | B88: LV Hybrid | C88: SUN-3.6K-SG03LP1-EU | D88: single-phase | E88: 3600 | F88: 4680 | G88: 500 | H88: 150 | I88: 125 | J88: 425 | K88: 2 | L88: 1+1 | M88: 13 | N88: 17 | O88: 48 | P88: 40-60 | Q88: seed_verify_datasheet | R88: Starter record for low-voltage hybrid inverter calculations.
A89: Deye | B89: LV Hybrid | C89: SUN-5K-SG03LP1-EU | D89: single-phase | E89: 5000 | F89: 6500 | G89: 500 | H89: 150 | I89: 125 | J89: 425 | K89: 2 | L89: 1+1 | M89: 13 | N89: 17 | O89: 48 | P89: 40-60 | Q89: seed_verify_datasheet | R89: Starter record for low-voltage hybrid inverter calculations.
A90: Deye | B90: LV Hybrid | C90: SUN-6K-SG03LP1-EU | D90: single-phase | E90: 6000 | F90: 7800 | G90: 500 | H90: 150 | I90: 125 | J90: 425 | K90: 2 | L90: 1+1 | M90: 13 | N90: 17 | O90: 48 | P90: 40-60 | Q90: seed_verify_datasheet | R90: Starter record for low-voltage hybrid inverter calculations.
A91: Deye | B91: LV Hybrid | C91: SUN-8K-SG01LP1-EU | D91: single-phase | E91: 8000 | F91: 10400 | G91: 500 | H91: 150 | I91: 125 | J91: 425 | K91: 2 | L91: 2+2 | M91: 26 | N91: 34 | O91: 48 | P91: 40-60 | Q91: seed_verify_datasheet | R91: Starter record; verify exact PV current and string inputs for selected market version.
A92: Growatt | B92: SPH TL BL-UP | C92: SPH 3000TL BL-UP | D92: single-phase | E92: 3000 | Q92: model_only_needs_datasheet | R92: Hybrid/storage inverter model candidate; datasheet parameters pending.
A93: Growatt | B93: SPH TL BL-UP | C93: SPH 3600TL BL-UP | D93: single-phase | E93: 3600 | Q93: model_only_needs_datasheet | R93: Hybrid/storage inverter model candidate; datasheet parameters pending.
A94: Growatt | B94: SPH TL BL-UP | C94: SPH 4000TL BL-UP | D94: single-phase | E94: 4000 | Q94: model_only_needs_datasheet | R94: Hybrid/storage inverter model candidate; datasheet parameters pending.
A95: Growatt | B95: SPH TL BL-UP | C95: SPH 4600TL BL-UP | D95: single-phase | E95: 4600 | Q95: model_only_needs_datasheet | R95: Hybrid/storage inverter model candidate; datasheet parameters pending.
A96: Growatt | B96: SPH TL BL-UP | C96: SPH 5000TL BL-UP | D96: single-phase | E96: 5000 | Q96: model_only_needs_datasheet | R96: Hybrid/storage inverter model candidate; datasheet parameters pending.
A97: Growatt | B97: SPH TL BL-UP | C97: SPH 6000TL BL-UP | D97: single-phase | E97: 6000 | Q97: model_only_needs_datasheet | R97: Hybrid/storage inverter model candidate; datasheet parameters pending.
A98: Growatt | B98: SPH TL3 BH-UP | C98: SPH 4000TL3 BH-UP | D98: three-phase | E98: 4000 | Q98: model_only_needs_datasheet | R98: Hybrid/storage inverter model candidate; datasheet parameters pending.
A99: Growatt | B99: SPH TL3 BH-UP | C99: SPH 5000TL3 BH-UP | D99: three-phase | E99: 5000 | Q99: model_only_needs_datasheet | R99: Hybrid/storage inverter model candidate; datasheet parameters pending.
A100: Growatt | B100: SPH TL3 BH-UP | C100: SPH 6000TL3 BH-UP | D100: three-phase | E100: 6000 | Q100: model_only_needs_datasheet | R100: Hybrid/storage inverter model candidate; datasheet parameters pending.
A101: Growatt | B101: SPH TL3 BH-UP | C101: SPH 7000TL3 BH-UP | D101: three-phase | E101: 7000 | Q101: model_only_needs_datasheet | R101: Hybrid/storage inverter model candidate; datasheet parameters pending.
A102: Growatt | B102: SPH TL3 BH-UP | C102: SPH 8000TL3 BH-UP | D102: three-phase | E102: 8000 | Q102: model_only_needs_datasheet | R102: Hybrid/storage inverter model candidate; datasheet parameters pending.
A103: Growatt | B103: SPH TL3 BH-UP | C103: SPH 10000TL3 BH-UP | D103: three-phase | E103: 10000 | Q103: model_only_needs_datasheet | R103: Hybrid/storage inverter model candidate; datasheet parameters pending.
... A126: Growatt | B126: WIT TL3-A-LV | C126: WIT 100KTL3-A-LV | D126: three-phase | E126: 100000 | Q126: model_only_needs_datasheet | R126: Commercial hybrid/storage inverter model candidate; datasheet parameters pending.
A127: MUST | B127: PV1800 VHM | C127: PV1800 VHM-2KW-24V | D127: single-phase | E127: 2000 | O127: 24 | Q127: model_only_needs_datasheet | R127: Hybrid inverter model candidate; datasheet parameters pending.
A128: MUST | B128: PV1800 VHM | C128: PV1800 VHM-3KW-24V | D128: single-phase | E128: 3000 | O128: 24 | Q128: model_only_needs_datasheet | R128: Hybrid inverter model candidate; datasheet parameters pending.
A129: MUST | B129: PV1800 VHM | C129: PV1800 VHM-4KW-48V | D129: single-phase | E129: 4000 | O129: 48 | Q129: model_only_needs_datasheet | R129: Hybrid inverter model candidate; datasheet parameters pending.
A130: MUST | B130: PV1800 VHM | C130: PV1800 VHM-5KW-48V | D130: single-phase | E130: 5000 | O130: 48 | Q130: model_only_needs_datasheet | R130: Hybrid inverter model candidate; datasheet parameters pending.
A131: MUST | B131: PV1800 PRO | C131: PV1800 PRO-3KW-24V | D131: single-phase | E131: 3000 | O131: 24 | Q131: model_only_needs_datasheet | R131: Hybrid inverter model candidate; datasheet parameters pending.
A132: MUST | B132: PV1800 PRO | C132: PV1800 PRO-5.2KW-48V | D132: single-phase | E132: 5200 | O132: 48 | Q132: model_only_needs_datasheet | R132: Hybrid inverter model candidate; datasheet parameters pending.
A133: MUST | B133: PV1800 PRO | C133: PV1800 PRO-6.2KW-48V | D133: single-phase | E133: 6200 | O133: 48 | Q133: model_only_needs_datasheet | R133: Hybrid inverter model candidate; datasheet parameters pending.
A134: MUST | B134: PV18 VPM | C134: PV18-3024 VPM | D134: single-phase | E134: 3000 | O134: 24 | Q134: model_only_needs_datasheet | R134: Hybrid inverter model candidate; datasheet parameters pending.
A135: MUST | B135: PV18 VPM | C135: PV18-5048 VPM | D135: single-phase | E135: 5000 | O135: 48 | Q135: model_only_needs_datasheet | R135: Hybrid inverter model candidate; datasheet parameters pending.
A136: MUST | B136: PV18 VPM | C136: PV18-5548 VPM | D136: single-phase | E136: 5500 | O136: 48 | Q136: model_only_needs_datasheet | R136: Hybrid inverter model candidate; datasheet parameters pending.
A137: MUST | B137: PV18 VPM | C137: PV18-6048 VPM | D137: single-phase | E137: 6000 | O137: 48 | Q137: model_only_needs_datasheet | R137: Hybrid inverter model candidate; datasheet parameters pending.
A138: MUST | B138: PV18 VHM | C138: PV18-3024 VHM | D138: single-phase | E138: 3000 | O138: 24 | Q138: model_only_needs_datasheet | R138: Hybrid inverter model candidate; datasheet parameters pending.
... A147: PowMr | B147: POW-HVM | C147: POW-HVM5.5K-48V-LIP | D147: single-phase | E147: 5500 | O147: 48 | Q147: model_only_needs_datasheet | R147: Model found in PowMr official catalog/manual references; datasheet parameters pending.
A148: PowMr | B148: POW-HVM | C148: POW-HVM5.5M | D148: single-phase | E148: 5500 | Q148: model_only_needs_datasheet | R148: Model found in PowMr official catalog/manual references; datasheet parameters pending.
A149: PowMr | B149: POW-HPM | C149: POW-HPM5.6KW | D149: single-phase | E149: 5600 | Q149: model_only_needs_datasheet | R149: Model found in PowMr official catalog/manual references; datasheet parameters pending.
A150: PowMr | B150: POW-SunSmart | C150: POW-SUNSMART-5.5KW-48V | D150: single-phase | E150: 5500 | O150: 48 | Q150: model_only_needs_datasheet | R150: Model found in PowMr official catalog/manual references; datasheet parameters pending.
A151: PowMr | B151: POW-SunSmart | C151: POW-SUNSMART-5.6KW-48V | D151: single-phase | E151: 5600 | O151: 48 | Q151: model_only_needs_datasheet | R151: Model found in PowMr official catalog/manual references; datasheet parameters pending.
A152: PowMr | B152: POW-VM | C152: POW-VM5K-III | D152: single-phase | E152: 5000 | Q152: model_only_needs_datasheet | R152: Model found in PowMr official catalog/manual references; datasheet parameters pending.
A153: PowMr | B153: POW-MAX | C153: POW-MAX-8KW | D153: single-phase | E153: 8000 | Q153: model_only_needs_datasheet | R153: Model found in PowMr official catalog/manual references; datasheet parameters pending.
A154: PowMr | B154: POW-SunSmart LVM | C154: POW-SunSmart LVM12K | D154: split-phase | E154: 12000 | O154: 48 | Q154: model_only_needs_datasheet | R154: Model found in PowMr official 110V hybrid inverter catalog; datasheet parameters pending.
...

Sheet Panels
A1: brand | B1: series | C1: model | D1: power_stc_w | E1: vmp_stc_v | F1: imp_stc_a | G1: voc_stc_v | H1: isc_stc_a | I1: temp_coeff_pmax_pct_c | J1: temp_coeff_voc_pct_c | K1: temp_coeff_isc_pct_c | L1: module_length_mm | M1: module_width_mm | N1: module_depth_mm | O1: data_status | P1: notes
A2: Astronergy | B2: ASTRO N5 | C2: CHSM54N-HC-430 | D2: 430 | O2: model_only_needs_datasheet | P2: Panel catalog model; datasheet parameters pending.
A3: Astronergy | B3: ASTRO N5 | C3: CHSM54N-HC-435 | D3: 435 | O3: model_only_needs_datasheet | P3: Panel catalog model; datasheet parameters pending.
A4: Astronergy | B4: ASTRO N5 | C4: CHSM54N-HC-440 | D4: 440 | O4: model_only_needs_datasheet | P4: Panel catalog model; datasheet parameters pending.
A5: Astronergy | B5: ASTRO N7 | C5: CHSM72N(DG)/F-BH-570 | D5: 570 | O5: model_only_needs_datasheet | P5: Panel catalog model; datasheet parameters pending.
A6: Astronergy | B6: ASTRO N7 | C6: CHSM72N(DG)/F-BH-575 | D6: 575 | O6: model_only_needs_datasheet | P6: Panel catalog model; datasheet parameters pending.
A7: Astronergy | B7: ASTRO N7 | C7: CHSM72N(DG)/F-BH-580 | D7: 580 | O7: model_only_needs_datasheet | P7: Panel catalog model; datasheet parameters pending.
A8: Astronergy | B8: ASTRO N7 | C8: CHSM66N(DG)/F-BH-615 | D8: 615 | O8: model_only_needs_datasheet | P8: Panel catalog model; datasheet parameters pending.
A9: Astronergy | B9: ASTRO N7 | C9: CHSM66N(DG)/F-BH-620 | D9: 620 | O9: model_only_needs_datasheet | P9: Panel catalog model; datasheet parameters pending.
A10: JA Solar | B10: DeepBlue 3.0 | C10: JAM54S30-410/MR | D10: 410 | O10: model_only_needs_datasheet | P10: Panel catalog model; datasheet parameters pending.
A11: JA Solar | B11: DeepBlue 3.0 | C11: JAM54S30-415/MR | D11: 415 | O11: model_only_needs_datasheet | P11: Panel catalog model; datasheet parameters pending.
A12: JA Solar | B12: DeepBlue 3.0 | C12: JAM54S30-420/MR | D12: 420 | O12: model_only_needs_datasheet | P12: Panel catalog model; datasheet parameters pending.
A13: JA Solar | B13: DeepBlue 3.0 Pro | C13: JAM54D40-440/LB | D13: 440 | O13: model_only_needs_datasheet | P13: Panel catalog model; datasheet parameters pending.
... A28: Jinko | B28: Tiger Neo N-type 66HL4M | C28: JKM620N-66HL4M-V | D28: 620 | O28: model_only_needs_datasheet | P28: Panel catalog model; datasheet parameters pending.
A29: Jinko | B29: Tiger Neo N-type 72HL4 | C29: JKM565N-72HL4-V | D29: 565 | E29: 43.28 | F29: 13.06 | G29: 51.7 | H29: 13.86 | I29: -0.29 | J29: -0.25 | K29: 0.045 | L29: 2278 | M29: 1134 | N29: 30 | O29: seed_verify_datasheet | P29: Starter record for string sizing tests.
A30: Jinko | B30: Tiger Neo N-type 72HL4 | C30: JKM570N-72HL4-V | D30: 570 | E30: 43.52 | F30: 13.1 | G30: 51.89 | H30: 13.89 | I30: -0.29 | J30: -0.25 | K30: 0.045 | L30: 2278 | M30: 1134 | N30: 30 | O30: seed_verify_datasheet | P30: Starter record for string sizing tests.
A31: Jinko | B31: Tiger Neo N-type 72HL4 | C31: JKM575N-72HL4-V | D31: 575 | E31: 43.76 | F31: 13.14 | G31: 52.08 | H31: 13.92 | I31: -0.29 | J31: -0.25 | K31: 0.045 | L31: 2278 | M31: 1134 | N31: 30 | O31: seed_verify_datasheet | P31: Starter record for string sizing tests.
A32: Jinko | B32: Tiger Neo N-type 72HL4 | C32: JKM580N-72HL4-V | D32: 580 | E32: 43.99 | F32: 13.19 | G32: 52.27 | H32: 13.96 | I32: -0.29 | J32: -0.25 | K32: 0.045 | L32: 2278 | M32: 1134 | N32: 30 | O32: seed_verify_datasheet | P32: Starter record for string sizing tests.
A33: Jinko | B33: Tiger Neo N-type 72HL4 | C33: JKM585N-72HL4-V | D33: 585 | E33: 44.23 | F33: 13.23 | G33: 52.46 | H33: 14 | I33: -0.29 | J33: -0.25 | K33: 0.045 | L33: 2278 | M33: 1134 | N33: 30 | O33: seed_verify_datasheet | P33: Starter record for string sizing tests.
A34: LONGi | B34: Hi-MO 6 Explorer | C34: LR5-54HTH-425M | D34: 425 | O34: model_only_needs_datasheet | P34: Panel catalog model; datasheet parameters pending.
A35: LONGi | B35: Hi-MO 6 Explorer | C35: LR5-54HTH-430M | D35: 430 | O35: model_only_needs_datasheet | P35: Panel catalog model; datasheet parameters pending.
A36: LONGi | B36: Hi-MO 6 Explorer | C36: LR5-54HTH-435M | D36: 435 | O36: model_only_needs_datasheet | P36: Panel catalog model; datasheet parameters pending.
A37: LONGi | B37: Hi-MO 7 | C37: LR5-72HGD-585M | D37: 585 | O37: model_only_needs_datasheet | P37: Panel catalog model; datasheet parameters pending.
A38: LONGi | B38: Hi-MO 7 | C38: LR5-72HGD-590M | D38: 590 | O38: model_only_needs_datasheet | P38: Panel catalog model; datasheet parameters pending.
A39: LONGi | B39: Hi-MO 7 | C39: LR5-72HGD-595M | D39: 595 | O39: model_only_needs_datasheet | P39: Panel catalog model; datasheet parameters pending.
A40: LONGi | B40: Hi-MO X6 | C40: LR5-54HTB-430M | D40: 430 | O40: model_only_needs_datasheet | P40: Panel catalog model; datasheet parameters pending.
A41: LONGi | B41: Hi-MO X6 | C41: LR5-54HTB-435M | D41: 435 | O41: model_only_needs_datasheet | P41: Panel catalog model; datasheet parameters pending.
A42: LONGi | B42: Hi-MO 6 | C42: LR5-72HTH-565M | D42: 565 | E42: 42.94 | F42: 13.16 | G42: 51.21 | H42: 14.01 | I42: -0.29 | J42: -0.23 | K42: 0.05 | L42: 2278 | M42: 1134 | N42: 35 | O42: seed_verify_datasheet | P42: Starter record for string sizing tests.
A43: LONGi | B43: Hi-MO 6 | C43: LR5-72HTH-570M | D43: 570 | E43: 43.13 | F43: 13.22 | G43: 51.4 | H43: 14.07 | I43: -0.29 | J43: -0.23 | K43: 0.05 | L43: 2278 | M43: 1134 | N43: 35 | O43: seed_verify_datasheet | P43: Starter record for string sizing tests.
A44: LONGi | B44: Hi-MO 6 | C44: LR5-72HTH-575M | D44: 575 | E44: 43.32 | F44: 13.28 | G44: 51.59 | H44: 14.14 | I44: -0.29 | J44: -0.23 | K44: 0.05 | L44: 2278 | M44: 1134 | N44: 35 | O44: seed_verify_datasheet | P44: Starter record for string sizing tests.
A45: LONGi | B45: Hi-MO 6 | C45: LR5-72HTH-580M | D45: 580 | E45: 43.51 | F45: 13.34 | G45: 51.78 | H45: 14.2 | I45: -0.29 | J45: -0.23 | K45: 0.05 | L45: 2278 | M45: 1134 | N45: 35 | O45: seed_verify_datasheet | P45: Starter record for string sizing tests.
A46: LONGi | B46: Hi-MO 6 | C46: LR5-72HTH-585M | D46: 585 | E46: 43.7 | F46: 13.39 | G46: 51.97 | H46: 14.26 | I46: -0.29 | J46: -0.23 | K46: 0.05 | L46: 2278 | M46: 1134 | N46: 35 | O46: seed_verify_datasheet | P46: Starter record for string sizing tests.
A47: SunPro | B47: SPDG N-type | C47: SPDG430-N108M10 | D47: 430 | O47: model_only_needs_datasheet | P47: Panel catalog model; datasheet parameters pending.
A48: SunPro | B48: SPDG N-type | C48: SPDG435-N108M10 | D48: 435 | O48: model_only_needs_datasheet | P48: Panel catalog model; datasheet parameters pending.
A49: SunPro | B49: SPDG N-type | C49: SPDG440-N108M10 | D49: 440 | O49: model_only_needs_datasheet | P49: Panel catalog model; datasheet parameters pending.
A50: SunPro | B50: SPDG N-type | C50: SPDG570-N144M10 | D50: 570 | O50: model_only_needs_datasheet | P50: Panel catalog model; datasheet parameters pending.
A51: SunPro | B51: SPDG N-type | C51: SPDG575-N144M10 | D51: 575 | O51: model_only_needs_datasheet | P51: Panel catalog model; datasheet parameters pending.
A52: SunPro | B52: SPDG N-type | C52: SPDG580-N144M10 | D52: 580 | O52: model_only_needs_datasheet | P52: Panel catalog model; datasheet parameters pending.
A53: SunPro | B53: SPDG N-type | C53: SPDG585-N144M10 | D53: 585 | O53: model_only_needs_datasheet | P53: Panel catalog model; datasheet parameters pending.
A54: Trina | B54: Vertex S+ | C54: TSM-NEG9R.25-430 | D54: 430 | O54: model_only_needs_datasheet | P54: Panel catalog model; datasheet parameters pending.
A55: Trina | B55: Vertex S+ | C55: TSM-NEG9R.25-435 | D55: 435 | O55: model_only_needs_datasheet | P55: Panel catalog model; datasheet parameters pending.
A56: Trina | B56: Vertex S+ | C56: TSM-NEG9R.25-440 | D56: 440 | O56: model_only_needs_datasheet | P56: Panel catalog model; datasheet parameters pending.
A57: Trina | B57: Vertex N | C57: TSM-NEG18R.28-500 | D57: 500 | O57: model_only_needs_datasheet | P57: Panel catalog model; datasheet parameters pending.
A58: Trina | B58: Vertex N | C58: TSM-NEG18R.28-505 | D58: 505 | O58: model_only_needs_datasheet | P58: Panel catalog model; datasheet parameters pending.
... A73: Ulica | B73: UL N-type | C73: UL-580M-144HV | D73: 580 | O73: model_only_needs_datasheet | P73: Panel catalog model; datasheet parameters pending.

Sheet Batteries
A1: brand | B1: series | C1: model | D1: chemistry | E1: nominal_energy_kwh | F1: usable_energy_kwh | G1: nominal_voltage_v | H1: capacity_ah | I1: cycle_life_min | J1: cycle_life_max | K1: communication | L1: bms | M1: compatibility | N1: data_status | O1: notes
A2: Pylontech | B2: US Series | C2: US5000 | D2: LiFePO4 | E2: 4.8 | G2: 48 | I2: 6000 | J2: 8000 | K2: CAN/RS485 | L2: Integrated BMS | M2: Deye compatible | N2: seed_verify_datasheet | O2: User-listed premium battery; verify exact usable energy and protocol settings.
A3: Pylontech | B3: Force L2 | C3: Force L2 | D3: LiFePO4 | I3: 6000 | J3: 8000 | K3: CAN/RS485 | L3: Integrated BMS | M3: Deye compatible | N3: model_only_needs_datasheet | O3: User-listed premium low-voltage stack; datasheet parameters pending.
A4: Pylontech | B4: Force H2 | C4: Force H2 | D4: LiFePO4 | I4: 6000 | J4: 8000 | K4: CAN/RS485 | L4: Integrated BMS | M4: Deye compatible | N4: model_only_needs_datasheet | O4: User-listed premium high-voltage stack; datasheet parameters pending.
A5: Dyness | B5: BX Series | C5: BX51100 | D5: LiFePO4 | E5: 5.12 | G5: 51.2 | H5: 100 | K5: CAN/RS485 | L5: Integrated BMS | M5: Deye compatible | N5: seed_verify_datasheet | O5: User-listed value battery; verify exact cycle life and protocol settings.
A6: Dyness | B6: PowerRack | C6: PowerRack | D6: LiFePO4 | K6: CAN/RS485 | L6: Integrated BMS | M6: Deye compatible | N6: model_only_needs_datasheet | O6: User-listed rack battery series; datasheet parameters pending.
A7: Dyness | B7: Tower | C7: Tower | D7: LiFePO4 | K7: CAN/RS485 | L7: Integrated BMS | M7: Deye compatible | N7: model_only_needs_datasheet | O7: User-listed stack battery series; datasheet parameters pending.
A8: Deye ESS | B8: SE Series | C8: SE-G5.1 | D8: LiFePO4 | E8: 5.12 | G8: 51.2 | H8: 100 | K8: CAN/RS485 | L8: Deye BMS | M8: Deye native | N8: seed_verify_datasheet | O8: Deye ESS model; native protocol expected; verify datasheet.
A9: Deye ESS | B9: SE Series | C9: SE-F5 | D9: LiFePO4 | E9: 5.12 | G9: 51.2 | H9: 100 | K9: CAN/RS485 | L9: Deye BMS | M9: Deye native | N9: model_only_needs_datasheet | O9: Deye ESS model; datasheet parameters pending.
A10: Deye ESS | B10: RW Series | C10: RW-F16 | D10: LiFePO4 | E10: 16 | G10: 51.2 | K10: CAN/RS485 | L10: Deye BMS | M10: Deye native | N10: seed_verify_datasheet | O10: Deye ESS high-capacity model; verify exact energy and current limits.
A11: Gobel Power | B11: Rack/Wall | C11: Gobel Power 5.12kWh 51.2V 100Ah | D11: LiFePO4 | E11: 5.12 | G11: 51.2 | H11: 100 | K11: CAN/RS485 | L11: JK/PACE BMS | M11: Deye compatible | N11: model_only_needs_datasheet | O11: User-listed mid-segment supplier; often EVE Grade A+ cells.
A12: Gobel Power | B12: Rack/Wall | C12: Gobel Power 10.24kWh 51.2V 200Ah | D12: LiFePO4 | E12: 10.24 | G12: 51.2 | H12: 200 | K12: CAN/RS485 | L12: JK/PACE BMS | M12: Deye compatible | N12: model_only_needs_datasheet | O12: User-listed mid-segment supplier; datasheet parameters pending.
A13: GSL Energy | B13: Wall/Rack | C13: GSL 5.12kWh 51.2V 100Ah | D13: LiFePO4 | E13: 5.12 | G13: 51.2 | H13: 100 | K13: CAN/RS485 | L13: Integrated BMS | M13: Deye compatible | N13: model_only_needs_datasheet | O13: User-listed supplier; EVE/CATL cells reported by user.
A14: GSL Energy | B14: Wall/Rack | C14: GSL 10.24kWh 51.2V 200Ah | D14: LiFePO4 | E14: 10.24 | G14: 51.2 | H14: 200 | K14: CAN/RS485 | L14: Integrated BMS | M14: Deye compatible | N14: model_only_needs_datasheet | O14: User-listed supplier; datasheet parameters pending.
A15: Felicity ESS | B15: LPBA Series | C15: LPBA48100-OL | D15: LiFePO4 | E15: 5.12 | G15: 51.2 | H15: 100 | K15: CAN/RS485 | L15: Integrated BMS | M15: Deye compatible | N15: model_only_needs_datasheet | O15: Common Felicity low-voltage model candidate; datasheet parameters pending.
A16: Felicity ESS | B16: LPBF Series | C16: LPBF48100-M | D16: LiFePO4 | E16: 5.12 | G16: 51.2 | H16: 100 | K16: CAN/RS485 | L16: Integrated BMS | M16: Deye compatible | N16: model_only_needs_datasheet | O16: Common Felicity low-voltage model candidate; datasheet parameters pending.
A17: HinaESS | B17: Rack/Commercial | C17: HinaESS 5.12kWh 51.2V 100Ah | D17: LiFePO4 | E17: 5.12 | G17: 51.2 | H17: 100 | K17: CAN/RS485 | L17: Integrated BMS | M17: Deye compatible | N17: model_only_needs_datasheet | O17: User-listed commercial battery supplier; datasheet parameters pending.
A18: HinaESS | B18: Rack/Commercial | C18: HinaESS 10.24kWh 51.2V 200Ah | D18: LiFePO4 | E18: 10.24 | G18: 51.2 | H18: 200 | K18: CAN/RS485 | L18: Integrated BMS | M18: Deye compatible | N18: model_only_needs_datasheet | O18: User-listed commercial battery supplier; datasheet parameters pending.
A19: Basen Green | B19: Rack/Wall | C19: Basen Green 5.12kWh 51.2V 100Ah | D19: LiFePO4 | E19: 5.12 | G19: 51.2 | H19: 100 | K19: CAN/RS485 | L19: Integrated BMS | M19: Deye compatible | N19: model_only_needs_datasheet | O19: OEM battery candidate; datasheet parameters pending.
A20: Basen Green | B20: Rack/Wall | C20: Basen Green 10.24kWh 51.2V 200Ah | D20: LiFePO4 | E20: 10.24 | G20: 51.2 | H20: 200 | K20: CAN/RS485 | L20: Integrated BMS | M20: Deye compatible | N20: model_only_needs_datasheet | O20: OEM battery candidate; datasheet parameters pending.
A21: HTE | B21: Rack/Wall | C21: HTE 5.12kWh 51.2V 100Ah | D21: LiFePO4 | E21: 5.12 | G21: 51.2 | H21: 100 | K21: CAN/RS485 | L21: Integrated BMS | M21: Deye compatible | N21: model_only_needs_datasheet | O21: OEM battery candidate; datasheet parameters pending.
A22: SRNE ESS | B22: Rack/Wall | C22: SRNE ESS 5.12kWh 51.2V 100Ah | D22: LiFePO4 | E22: 5.12 | G22: 51.2 | H22: 100 | K22: CAN/RS485 | L22: Integrated BMS | M22: Deye compatible | N22: model_only_needs_datasheet | O22: OEM battery candidate; datasheet parameters pending.
... A25: EVE Energy ESS | B25: Rack/Wall | C25: EVE Energy ESS 5.12kWh 51.2V 100Ah | D25: LiFePO4 | E25: 5.12 | G25: 51.2 | H25: 100 | K25: CAN/RS485 | L25: Integrated BMS | M25: Deye compatible | N25: model_only_needs_datasheet | O25: OEM battery candidate; datasheet parameters pending.

Sheet DropdownLists
A1: Выпадающие списки (Dropdown lists)
A2: Модели инверторов (Inverter models) | B2: Модели панелей (Panel models) | C2: Модели АКБ (Battery models) | D2: Типы кровли (Roof types) | E2: Способы прокладки (Installation methods) | F2: Варианты молниезащиты (Lightning options) | G2: Системы заземления (Earthing systems) | H2: Тарифные регионы (Tariff regions) | I2: Режимы тарифов (Tariff modes)
A3: ANJ-3.2KW-24V | B3: CHSM54N-HC-430 | C3: US5000 | D3: Metal tile | E3: Open air | F3: No external LPS | G3: TN-S | H3: Moscow starter | I3: Single-rate
A4: ANJ-3.6KW-24V | B4: CHSM54N-HC-435 | C4: Force L2 | D4: Standing seam | E4: Conduit or trunking | F4: External LPS | G4: TN-C-S | H4: Saint Petersburg starter | I4: Day-night
A5: ANJ-4.2KW-24V | B5: CHSM54N-HC-440 | C5: Force H2 | D5: Trapezoidal sheet | E5: Thermal insulation | F5: Overhead supply | G5: TT | H5: Krasnodar starter
A6: ANJ-6.2KW-48V | B6: CHSM72N(DG)/F-BH-570 | C6: BX51100 | D6: Flat roof | F6: Long outdoor DC route | G6: IT | H6: Rostov-on-Don starter
A7: ANJ-8.2KW-48V | B7: CHSM72N(DG)/F-BH-575 | C7: PowerRack | D7: Ground mount | H7: Yekaterinburg starter
A8: ANJ-10.2KW-48V | B8: CHSM72N(DG)/F-BH-580 | C8: Tower
A9: ANJ-11KW-48V | B9: CHSM66N(DG)/F-BH-615 | C9: SE-G5.1
A10: ANJ-12KW-48V | B10: CHSM66N(DG)/F-BH-620 | C10: SE-F5
A11: SUN-3K-SG04LP1-24-EU | B11: JAM54S30-410/MR | C11: RW-F16
A12: SUN-3K-SG04LP1-EU | B12: JAM54S30-415/MR | C12: Gobel Power 5.12kWh 51.2V 100Ah
A13: SUN-3.6K-SG05LP1-EU-AM2-P | B13: JAM54S30-420/MR | C13: Gobel Power 10.24kWh 51.2V 200Ah
A14: SUN-5K-SG05LP1-EU-AM2-P | B14: JAM54D40-440/LB | C14: GSL 5.12kWh 51.2V 100Ah
A15: SUN-6K-SG05LP1-EU-AM2-P | B15: JAM54D40-445/LB | C15: GSL 10.24kWh 51.2V 200Ah
A16: SUN-8K-SG05LP1-EU-AM2-P | B16: JAM72D42-575/LB | C16: LPBA48100-OL
A17: SUN-10K-SG02LP1-EU-AM3-P | B17: JAM72D42-580/LB | C17: LPBF48100-M
A18: SUN-12K-SG02LP1-EU-AM3-P | B18: JAM72D42-585/LB | C18: HinaESS 5.12kWh 51.2V 100Ah
A19: SUN-14K-SG01LP1-EU-AM3-P | B19: JAM72D42-590/LB | C19: HinaESS 10.24kWh 51.2V 200Ah
... A26: SUN-12K-SG05LP3-EU-SM2 | B26: JKM475N-60HL4-V | C26: EVE Energy ESS 5.12kWh 51.2V 100Ah
A27: SUN-14K-SG05LP3-EU-SM2 | B27: JKM610N-66HL4M-V
A28: SUN-15K-SG05LP3-EU-SM2 | B28: JKM615N-66HL4M-V
A29: SUN-16K-SG05LP3-EU-SM2 | B29: JKM620N-66HL4M-V
A30: SUN-18K-SG05LP3-EU-SM2 | B30: JKM565N-72HL4-V
A31: SUN-20K-SG05LP3-EU-SM2 | B31: JKM570N-72HL4-V
A32: SUN-10K-SG01HP3-EU-AM2 | B32: JKM575N-72HL4-V
A33: SUN-12K-SG01HP3-EU-AM2 | B33: JKM580N-72HL4-V
A34: SUN-15K-SG01HP3-EU-AM2 | B34: JKM585N-72HL4-V
A35: SUN-20K-SG01HP3-EU-AM2 | B35: LR5-54HTH-425M
A36: SUN-25K-SG01HP3-EU-AM2 | B36: LR5-54HTH-430M
A37: SUN-30K-SG02HP3-EU-AM3 | B37: LR5-54HTH-435M
A38: SUN-40K-SG01HP3-EU-BM4 | B38: LR5-72HGD-585M
... A74: SUN-35K-G04 | B74: UL-580M-144HV
A75: SUN-40K-G04
A76: SUN-45K-G04
A77: SUN-50K-G04
A78: SUN-60K-G04P3-EU-AM4
A79: SUN-70K-G04P3-EU-AM4
A80: SUN-75K-G04P3-EU-AM4
A81: SUN-80K-G04P3-EU-AM4
A82: SUN-100K-G03
A83: SUN-110K-G03
A84: SUN-120K-G01P3-EU-AM8
A85: SUN-125K-G01P3-EU-AM8
A86: SUN-130K-G01P3-EU-AM8
... A186: S6-EH3P50K-H

Sheet Mounting
A1: Количество крепежа (Mounting quantity) | B1: Значение (Value) | C1: Ед. изм. (Unit) | D1: Формула / смысл (Formula / meaning)
A2: Тип кровли (Roof type) | B2: =Inputs!B11 | D2: Из листа Inputs (From Inputs)
A3: Всего панелей (Total panels) | B3: =Inputs!B12 | C3: pcs | D3: Из листа Inputs (From Inputs)
A4: Панелей в ряду (Panels per row) | B4: =Inputs!B13 | C4: pcs | D4: Из листа Inputs (From Inputs)
A5: Ряды (Rows) | B5: =ROUNDUP(B3/B4,0) | C5: rows | D5: Calculated from total panels and panels per row
A6: Линии реек (Rail lines) | B6: =B5*2 | C6: pcs | D6: Две линии реек на ряд (Two rail lines per row)
A7: Оценочная длина реек (Estimated rail length) | B7: =B3*Inputs!B15*2 | C7: m | D7: Всего панелей x длина рейки на панель x 2 (Total panels x rail length per panel x 2)
A8: Стыки реек (Rail joints) | B8: =MAX(0,ROUNDUP(B7/Inputs!B14,0)-B6) | C8: pcs | D8: Оценка по длине реек и складской длине (Estimated from rail length and stock length)
A9: Запас (Reserve) | B9: =Inputs!B16 | C9: % | D9: Дополнительный запас количества (Extra quantity reserve)
A10: Компонент (Component) | B10: Количество (Quantity) | C10: Ед. изм. (Unit) | D10: Примечания (Notes)
A11: Крюки / фальцевые зажимы / наземные стойки (Roof hooks / seam clamps / ground posts) | B11: =ROUNDUP((SUMIFS(MountingRules!D:D,MountingRules!A:A,B2,MountingRules!B:B,"Roof hook")+SUMIFS(MountingRules!D:D,MountingRules!A:A,B2,MountingRules!B:B,"Mini rail clamp")+SUMIFS(MountingRules!E:E,MountingRules!A:A,B2,MountingRules!B:B,"Ground post"))*B3*(1+B9/100),0) | C11: pcs | D11: Крюки, фальцевые зажимы или наземные стойки по типу установки (Hooks, seam clamps, or ground posts depending on installation type)
A12: Мини-рельсы (Mini-rails) | B12: =ROUNDUP(SUMIFS(MountingRules!D:D,MountingRules!A:A,B2,MountingRules!B:B,"*Mini rail*")*B3*(1+B9/100),0) | C12: pcs | D12: Для кровельных систем с мини-рельсами (Used for mini-rail roof systems)
A13: Рейки (Rails) | B13: =ROUNDUP(B7/Inputs!B12*(1+B9/100),0) | C13: pcs | D13: Складские отрезки реек (Rail stock pieces)
A14: Соединители реек (Rail connectors) | B14: =ROUNDUP(B8*2*(1+B9/100),0) | C14: pcs | D14: Обычно два на стык рейки (Usually two per rail joint)
A15: Крайние прижимы (End clamps) | B15: =ROUNDUP(B5*4*(1+B9/100),0) | C15: pcs | D15: Четыре на ряд (Four per row)
A16: Средние прижимы (Middle clamps) | B16: =ROUNDUP(MAX(0,(B3-B5)*2)*(1+B9/100),0) | C16: pcs | D16: Два на промежуток между панелями в ряду (Two per gap between panels in a row)
A17: Комплекты болтов (Bolt sets) | B17: =ROUNDUP((SUMIFS(MountingRules!D:D,MountingRules!A:A,B2,MountingRules!B:B,"Bolt set")+SUMIFS(MountingRules!D:D,MountingRules!A:A,B2,MountingRules!B:B,"Self-drilling screw set"))*B3*(1+B9/100),0) | C17: pcs | D17: Запас крепежа (Fastener allowance)
A18: Клипсы заземления (Grounding clips) | B18: =ROUNDUP(B3*(1+B9/100),0) | C18: pcs | D18: Стартово один на панель (One per panel starter assumption)
A19: Кабельные клипсы (Cable clips) | B19: =ROUNDUP(B3*2*(1+B9/100),0) | C19: pcs | D19: Стартово два на панель (Two per panel starter assumption)

Sheet Equipment
A1: Category | B1: Показатель (Item) | C1: Количество (Quantity) | D1: Ед. изм. (Unit) | E1: Примечания (Notes)
A2: Инвертор (Inverter) | B2: =Inputs!B3 | C2: 1 | D2: pcs | E2: Выбранный инвертор (Selected inverter)
A3: Solar panels | B3: =Inputs!B4 | C3: =Inputs!B12 | D3: pcs | E3: Total panel quantity
A4: АКБ (Battery) | B4: =Inputs!B9 | C4: =Inputs!B10 | D4: pcs | E4: Selected battery quantity
A5: Battery energy | B5: =Inputs!B9&" total nominal energy" | C5: =Results!B29 | D5: kWh | E5: Total nominal battery energy
A6: Mounting | B6: Крюки / фальцевые зажимы / наземные стойки (Roof hooks / seam clamps / ground posts) | C6: =Mounting!B11 | D6: pcs | E6: From Mounting sheet
A7: Mounting | B7: Мини-рельсы (Mini-rails) | C7: =Mounting!B12 | D7: pcs | E7: From Mounting sheet
A8: Mounting | B8: Рейки (Rails) | C8: =Mounting!B13 | D8: pcs | E8: From Mounting sheet
A9: Mounting | B9: Соединители реек (Rail connectors) | C9: =Mounting!B14 | D9: pcs | E9: From Mounting sheet
A10: Mounting | B10: Крайние прижимы (End clamps) | C10: =Mounting!B15 | D10: pcs | E10: From Mounting sheet
A11: Mounting | B11: Средние прижимы (Middle clamps) | C11: =Mounting!B16 | D11: pcs | E11: From Mounting sheet
A12: Mounting | B12: Комплекты болтов (Bolt sets) | C12: =Mounting!B17 | D12: pcs | E12: From Mounting sheet
A13: Mounting | B13: Клипсы заземления (Grounding clips) | C13: =Mounting!B18 | D13: pcs | E13: From Mounting sheet
A14: Mounting | B14: Кабельные клипсы (Cable clips) | C14: =Mounting!B19 | D14: pcs | E14: From Mounting sheet
A15: Protection | B15: PV cable red | C15: =CableProtection!B2 | D15: m | E15: From CableProtection sheet
A16: Protection | B16: PV cable black | C16: =CableProtection!B3 | D16: m | E16: From CableProtection sheet
A17: Protection | B17: PE cable | C17: =CableProtection!B4 | D17: m | E17: From CableProtection sheet
A18: Protection | B18: DC string fuses | C18: =CableProtection!B5 | D18: pcs | E18: From CableProtection sheet
A19: Protection | B19: DC isolator | C19: =CableProtection!B6 | D19: pcs | E19: From CableProtection sheet
A20: Protection | B20: DC SPD Type 2 | C20: =CableProtection!B7 | D20: pcs | E20: From CableProtection sheet
A21: Protection | B21: AC breaker | C21: =CableProtection!B8 | D21: pcs | E21: From CableProtection sheet
A22: Protection | B22: AC SPD Type 2 | C22: =CableProtection!B9 | D22: pcs | E22: From CableProtection sheet
A23: Protection | B23: AC cable | C23: =CableProtection!B10 | D23: m | E23: From CableProtection sheet
A24: Protection | B24: Battery DC cable pair | C24: =CableProtection!B11 | D24: pair | E24: From CableProtection sheet
A25: Protection | B25: Battery fuse or breaker | C25: =CableProtection!B12 | D25: pcs | E25: From CableProtection sheet
A26: Sizing | B26: Recommended DC cable section | C26: =CableProtection!B15 | D26: mm2 | E26: Starter sizing; verify installation method
A27: Sizing | B27: DC voltage drop | C27: =CableProtection!B16 | D27: % | E27: Starter voltage-drop estimate
A28: Sizing | B28: Recommended AC cable section | C28: =CableProtection!B19 | D28: mm2 | E28: Starter sizing; verify installation method
A29: Sizing | B29: AC voltage drop | C29: =CableProtection!B20 | D29: % | E29: Starter voltage-drop estimate
A30: Sizing | B30: Recommended battery cable section | C30: =CableProtection!B24 | D30: mm2 | E30: Starter sizing; verify installation method
A31: Sizing | B31: Estimated battery current | C31: =CableProtection!B23 | D31: A | E31: Inverter power / battery voltage
A32: Sizing | B32: Коэффициент снижения нагрузки кабеля (Cable derating factor) | C32: =CableProtection!B30 | D32: factor | E32: Grouping x ambient derating
A33: Protection | B33: Recommended SPD type | C33: =CableProtection!B28 | E33: Starter selection; verify local standards
A34: Protection | B34: Система заземления AC (AC earthing system) | C34: =CableProtection!B29 | E34: Selected earthing checklist
A35: Documentation | B35: Datasheet verification | C35: 1 | D35: task | E35: Required before commercial use

Sheet CableProtection
A1: Cable / Protection item | B1: Количество (Quantity) | C1: Ед. изм. (Unit) | D1: Формула / смысл (Formula / meaning)
A2: PV cable red | B2: =Inputs!B17 | C2: m | D2: Длина DC кабеля (DC cable route length)
A3: PV cable black | B3: =Inputs!B17 | C3: m | D3: Длина DC кабеля (DC cable route length)
A4: PE cable | B4: =Inputs!B19 | C4: m | D4: Grounding route length
A5: DC string fuses | B5: =IF(Inputs!B8>1,Inputs!B8*2,0) | C5: pcs | D5: Used when strings per MPPT > 1
A6: DC isolator | B6: =1 | C6: pcs | D6: Starter quantity
A7: DC SPD Type 2 | B7: =1 | C7: pcs | D7: Starter quantity
A8: AC breaker | B8: =1 | C8: pcs | D8: Starter quantity; rating must be selected
A9: AC SPD Type 2 | B9: =1 | C9: pcs | D9: Starter quantity
A10: AC cable | B10: =Inputs!B18 | C10: m | D10: Длина AC кабеля (AC cable route length)
A11: Battery DC cable pair | B11: =1 | C11: pair | D11: Starter quantity
A12: Battery fuse or breaker | B12: =1 | C12: pcs | D12: Starter quantity; rating must be selected
A13: Protection design status | B13: ="VERIFY" | D13: VERIFY until ratings and cable sections are selected
A15: Sizing result | B15: =MAX(4,LOOKUP((Results!B12*Inputs!B8)/B30,CableSizing!B:B,CableSizing!A:A)) | C15: Ед. изм. (Unit) | D15: Формула / смысл (Formula / meaning)
A16: Recommended DC cable section | B16: =ROUND(2*Inputs!B17*Results!B12*Inputs!B8*0.0175/(B15*Results!B17)*100,2) | C16: mm2 | D16: Based on PV operating current
A17: DC voltage drop | B17: =LOOKUP(INDEX(Panels!H:H,MATCH(Inputs!B4,Panels!C:C,0))*1.25,{0,16,20,25,32},{16,20,25,32,40}) | C17: % | D17: 2 x length x current x copper resistance / section / voltage
A18: Suggested DC fuse rating | B18: =ROUND(INDEX(Inverters!E:E,MATCH(Inputs!B3,Inverters!C:C,0))/IF(INDEX(Inverters!D:D,MATCH(Inputs!B3,Inverters!C:C,0))="three-phase",692.8,230),1) | C18: A | D18: Based on string short-circuit current
A19: Estimated AC current | B19: =MAX(2.5,LOOKUP(B18/B30,CableSizing!B:B,CableSizing!A:A)) | C19: A | D19: Based on inverter AC power and phase
A20: Recommended AC cable section | B20: =ROUND(IF(INDEX(Inverters!D:D,MATCH(Inputs!B3,Inverters!C:C,0))="three-phase",1.732*Inputs!B18*B18*0.0175/(B19*400)*100,2*Inputs!B18*B18*0.0175/(B19*230)*100),2) | C20: mm2 | D20: Based on estimated AC current
A21: AC voltage drop | B21: =LOOKUP(B18*1.25,{0,16,20,25,32,40,50,63,80,100,125,160},{16,20,25,32,40,50,63,80,100,125,160,200}) | C21: % | D21: Starter single/three-phase voltage-drop estimate
A22: Suggested AC breaker rating | C22: A | D22: Next common rating above AC current
A23: Estimated battery current | B23: =ROUND(INDEX(Inverters!E:E,MATCH(Inputs!B3,Inverters!C:C,0))/INDEX(Batteries!G:G,MATCH(Inputs!B9,Batteries!C:C,0)),1) | C23: A | D23: AC power / battery nominal voltage
A24: Recommended battery cable section | B24: =MAX(16,LOOKUP(B23/B30,CableSizing!B:B,CableSizing!A:A)) | C24: mm2 | D24: Based on estimated battery current
A25: Suggested battery breaker rating | B25: =LOOKUP(B23*1.25,{0,63,80,100,125,160,200,250},{63,80,100,125,160,200,250,315}) | C25: A | D25: Next common rating above battery current
A26: Sizing status | B26: ="VERIFY" | D26: VERIFY until local standards and datasheets are checked
A28: Advanced protection result | B28: =IF(Inputs!B23="External LPS","Type 1+2 DC/AC SPD",IF(Inputs!B23="Overhead supply","Type 1+2 AC SPD + Type 2 DC SPD",IF(Inputs!B23="Long outdoor DC route","Type 2 DC SPD near inverter and array","Type 2 DC/AC SPD"))) | C28: Ед. изм. (Unit) | D28: Формула / смысл (Formula / meaning)
A29: Recommended SPD type | B29: =Inputs!B24 | D29: Based on selected lightning protection condition
A30: Система заземления AC (AC earthing system) | B30: =MAX(0.1,Inputs!B21*Inputs!B22) | D30: Selected earthing system checklist
A31: Combined cable derating factor | B31: =INDEX(CableSizing!B:B,MATCH(B15,CableSizing!A:A,0))*B30 | C31: factor | D31: Grouping derating x ambient derating
A32: Derated DC cable ampacity | B32: ="VERIFY" | C32: A | D32: Selected DC cable ampacity after derating
A33: Advanced protection status | D33: VERIFY until local standards are checked

Sheet BulkCompatibility
A1: Scenario | B1: Инвертор (Inverter) | C1: Панель (Panel) | D1: АКБ (Battery) | E1: Panels/string | F1: Strings/MPPT | G1: Cold string Voc | H1: Hot string Vmp | I1: PV voltage | J1: PV current | K1: АКБ (Battery) | L1: Overall | M1: Примечания (Notes)
A2: Residential 5kW Deye | B2: SUN-5K-SG03LP1-EU | C2: JKM575N-72HL4-V | D2: US5000 | E2: 8 | F2: 1 | G2: =ROUND(INDEX(Panels!G:G,MATCH(C2,Panels!C:C,0))*(1+(INDEX(Panels!J:J,MATCH(C2,Panels!C:C,0))/100)*(Inputs!B5-25))*E2,1) | H2: =ROUND(INDEX(Panels!E:E,MATCH(C2,Panels!C:C,0))*(1+(INDEX(Panels!J:J,MATCH(C2,Panels!C:C,0))/100)*(Inputs!B6-25))*E2,1) | I2: =IF(OR(INDEX(Inverters!Q:Q,MATCH(B2,Inverters!C:C,0))="model_only_needs_datasheet",INDEX(Panels!O:O,MATCH(C2,Panels!C:C,0))="model_only_needs_datasheet"),"VERIFY",IF(AND(G2<INDEX(Inverters!G:G,MATCH(B2,Inverters!C:C,0)),H2>=INDEX(Inverters!I:I,MATCH(B2,Inverters!C:C,0)),H2<=INDEX(Inverters!J:J,MATCH(B2,Inverters!C:C,0))),"PASS","FAIL")) | J2: =IF(OR(INDEX(Inverters!Q:Q,MATCH(B2,Inverters!C:C,0))="model_only_needs_datasheet",INDEX(Panels!O:O,MATCH(C2,Panels!C:C,0))="model_only_needs_datasheet"),"VERIFY",IF(INDEX(Panels!F:F,MATCH(C2,Panels!C:C,0))*F2<=INDEX(Inverters!M:M,MATCH(B2,Inverters!C:C,0)),"PASS","FAIL")) | K2: =IF(ISNUMBER(SEARCH("Deye",INDEX(Batteries!M:M,MATCH(D2,Batteries!C:C,0)))),"PASS","VERIFY") | L2: =IF(OR(I2="FAIL",J2="FAIL"),"FAIL",IF(OR(I2="VERIFY",J2="VERIFY",K2="VERIFY",INDEX(Inverters!Q:Q,MATCH(B2,Inverters!C:C,0))="model_only_needs_datasheet",INDEX(Panels!O:O,MATCH(C2,Panels!C:C,0))="model_only_needs_datasheet",INDEX(Batteries!N:N,MATCH(D2,Batteries!C:C,0))="model_only_needs_datasheet"),"VERIFY","PASS")) | M2: Starter Deye LV scenario.
A3: Residential 8kW Deye | B3: SUN-8K-SG01LP1-EU | C3: JKM575N-72HL4-V | D3: US5000 | E3: 8 | F3: 2 | G3: =ROUND(INDEX(Panels!G:G,MATCH(C3,Panels!C:C,0))*(1+(INDEX(Panels!J:J,MATCH(C3,Panels!C:C,0))/100)*(Inputs!B5-25))*E3,1) | H3: =ROUND(INDEX(Panels!E:E,MATCH(C3,Panels!C:C,0))*(1+(INDEX(Panels!J:J,MATCH(C3,Panels!C:C,0))/100)*(Inputs!B6-25))*E3,1) | I3: =IF(OR(INDEX(Inverters!Q:Q,MATCH(B3,Inverters!C:C,0))="model_only_needs_datasheet",INDEX(Panels!O:O,MATCH(C3,Panels!C:C,0))="model_only_needs_datasheet"),"VERIFY",IF(AND(G3<INDEX(Inverters!G:G,MATCH(B3,Inverters!C:C,0)),H3>=INDEX(Inverters!I:I,MATCH(B3,Inverters!C:C,0)),H3<=INDEX(Inverters!J:J,MATCH(B3,Inverters!C:C,0))),"PASS","FAIL")) | J3: =IF(OR(INDEX(Inverters!Q:Q,MATCH(B3,Inverters!C:C,0))="model_only_needs_datasheet",INDEX(Panels!O:O,MATCH(C3,Panels!C:C,0))="model_only_needs_datasheet"),"VERIFY",IF(INDEX(Panels!F:F,MATCH(C3,Panels!C:C,0))*F3<=INDEX(Inverters!M:M,MATCH(B3,Inverters!C:C,0)),"PASS","FAIL")) | K3: =IF(ISNUMBER(SEARCH("Deye",INDEX(Batteries!M:M,MATCH(D3,Batteries!C:C,0)))),"PASS","VERIFY") | L3: =IF(OR(I3="FAIL",J3="FAIL"),"FAIL",IF(OR(I3="VERIFY",J3="VERIFY",K3="VERIFY",INDEX(Inverters!Q:Q,MATCH(B3,Inverters!C:C,0))="model_only_needs_datasheet",INDEX(Panels!O:O,MATCH(C3,Panels!C:C,0))="model_only_needs_datasheet",INDEX(Batteries!N:N,MATCH(D3,Batteries!C:C,0))="model_only_needs_datasheet"),"VERIFY","PASS")) | M3: Starter two-string Deye LV scenario.
A4: Residential 6kW Deye | B4: SUN-6K-SG03LP1-EU | C4: LR5-72HTH-580M | D4: BX51100 | E4: 8 | F4: 1 | G4: =ROUND(INDEX(Panels!G:G,MATCH(C4,Panels!C:C,0))*(1+(INDEX(Panels!J:J,MATCH(C4,Panels!C:C,0))/100)*(Inputs!B5-25))*E4,1) | H4: =ROUND(INDEX(Panels!E:E,MATCH(C4,Panels!C:C,0))*(1+(INDEX(Panels!J:J,MATCH(C4,Panels!C:C,0))/100)*(Inputs!B6-25))*E4,1) | I4: =IF(OR(INDEX(Inverters!Q:Q,MATCH(B4,Inverters!C:C,0))="model_only_needs_datasheet",INDEX(Panels!O:O,MATCH(C4,Panels!C:C,0))="model_only_needs_datasheet"),"VERIFY",IF(AND(G4<INDEX(Inverters!G:G,MATCH(B4,Inverters!C:C,0)),H4>=INDEX(Inverters!I:I,MATCH(B4,Inverters!C:C,0)),H4<=INDEX(Inverters!J:J,MATCH(B4,Inverters!C:C,0))),"PASS","FAIL")) | J4: =IF(OR(INDEX(Inverters!Q:Q,MATCH(B4,Inverters!C:C,0))="model_only_needs_datasheet",INDEX(Panels!O:O,MATCH(C4,Panels!C:C,0))="model_only_needs_datasheet"),"VERIFY",IF(INDEX(Panels!F:F,MATCH(C4,Panels!C:C,0))*F4<=INDEX(Inverters!M:M,MATCH(B4,Inverters!C:C,0)),"PASS","FAIL")) | K4: =IF(ISNUMBER(SEARCH("Deye",INDEX(Batteries!M:M,MATCH(D4,Batteries!C:C,0)))),"PASS","VERIFY") | L4: =IF(OR(I4="FAIL",J4="FAIL"),"FAIL",IF(OR(I4="VERIFY",J4="VERIFY",K4="VERIFY",INDEX(Inverters!Q:Q,MATCH(B4,Inverters!C:C,0))="model_only_needs_datasheet",INDEX(Panels!O:O,MATCH(C4,Panels!C:C,0))="model_only_needs_datasheet",INDEX(Batteries!N:N,MATCH(D4,Batteries!C:C,0))="model_only_needs_datasheet"),"VERIFY","PASS")) | M4: Starter LONGi plus Dyness scenario.
A5: Commercial 10kW Deye | B5: SUN-10K-SG02LP1-EU-AM3-P | C5: TSM-NEG18R.28-500 | D5: SE-G5.1 | E5: 8 | F5: 1 | G5: =ROUND(INDEX(Panels!G:G,MATCH(C5,Panels!C:C,0))*(1+(INDEX(Panels!J:J,MATCH(C5,Panels!C:C,0))/100)*(Inputs!B5-25))*E5,1) | H5: =ROUND(INDEX(Panels!E:E,MATCH(C5,Panels!C:C,0))*(1+(INDEX(Panels!J:J,MATCH(C5,Panels!C:C,0))/100)*(Inputs!B6-25))*E5,1) | I5: =IF(OR(INDEX(Inverters!Q:Q,MATCH(B5,Inverters!C:C,0))="model_only_needs_datasheet",INDEX(Panels!O:O,MATCH(C5,Panels!C:C,0))="model_only_needs_datasheet"),"VERIFY",IF(AND(G5<INDEX(Inverters!G:G,MATCH(B5,Inverters!C:C,0)),H5>=INDEX(Inverters!I:I,MATCH(B5,Inverters!C:C,0)),H5<=INDEX(Inverters!J:J,MATCH(B5,Inverters!C:C,0))),"PASS","FAIL")) | J5: =IF(OR(INDEX(Inverters!Q:Q,MATCH(B5,Inverters!C:C,0))="model_only_needs_datasheet",INDEX(Panels!O:O,MATCH(C5,Panels!C:C,0))="model_only_needs_datasheet"),"VERIFY",IF(INDEX(Panels!F:F,MATCH(C5,Panels!C:C,0))*F5<=INDEX(Inverters!M:M,MATCH(B5,Inverters!C:C,0)),"PASS","FAIL")) | K5: =IF(ISNUMBER(SEARCH("Deye",INDEX(Batteries!M:M,MATCH(D5,Batteries!C:C,0)))),"PASS","VERIFY") | L5: =IF(OR(I5="FAIL",J5="FAIL"),"FAIL",IF(OR(I5="VERIFY",J5="VERIFY",K5="VERIFY",INDEX(Inverters!Q:Q,MATCH(B5,Inverters!C:C,0))="model_only_needs_datasheet",INDEX(Panels!O:O,MATCH(C5,Panels!C:C,0))="model_only_needs_datasheet",INDEX(Batteries!N:N,MATCH(D5,Batteries!C:C,0))="model_only_needs_datasheet"),"VERIFY","PASS")) | M5: Model-only scenario; datasheet values pending.
A6: Hybrid 12kW Deye | B6: SUN-12K-SG02LP1-EU-AM3-P | C6: JAM54D40-440/LB | D6: SE-G5.1 | E6: 8 | F6: 1 | G6: =ROUND(INDEX(Panels!G:G,MATCH(C6,Panels!C:C,0))*(1+(INDEX(Panels!J:J,MATCH(C6,Panels!C:C,0))/100)*(Inputs!B5-25))*E6,1) | H6: =ROUND(INDEX(Panels!E:E,MATCH(C6,Panels!C:C,0))*(1+(INDEX(Panels!J:J,MATCH(C6,Panels!C:C,0))/100)*(Inputs!B6-25))*E6,1) | I6: =IF(OR(INDEX(Inverters!Q:Q,MATCH(B6,Inverters!C:C,0))="model_only_needs_datasheet",INDEX(Panels!O:O,MATCH(C6,Panels!C:C,0))="model_only_needs_datasheet"),"VERIFY",IF(AND(G6<INDEX(Inverters!G:G,MATCH(B6,Inverters!C:C,0)),H6>=INDEX(Inverters!I:I,MATCH(B6,Inverters!C:C,0)),H6<=INDEX(Inverters!J:J,MATCH(B6,Inverters!C:C,0))),"PASS","FAIL")) | J6: =IF(OR(INDEX(Inverters!Q:Q,MATCH(B6,Inverters!C:C,0))="model_only_needs_datasheet",INDEX(Panels!O:O,MATCH(C6,Panels!C:C,0))="model_only_needs_datasheet"),"VERIFY",IF(INDEX(Panels!F:F,MATCH(C6,Panels!C:C,0))*F6<=INDEX(Inverters!M:M,MATCH(B6,Inverters!C:C,0)),"PASS","FAIL")) | K6: =IF(ISNUMBER(SEARCH("Deye",INDEX(Batteries!M:M,MATCH(D6,Batteries!C:C,0)))),"PASS","VERIFY") | L6: =IF(OR(I6="FAIL",J6="FAIL"),"FAIL",IF(OR(I6="VERIFY",J6="VERIFY",K6="VERIFY",INDEX(Inverters!Q:Q,MATCH(B6,Inverters!C:C,0))="model_only_needs_datasheet",INDEX(Panels!O:O,MATCH(C6,Panels!C:C,0))="model_only_needs_datasheet",INDEX(Batteries!N:N,MATCH(D6,Batteries!C:C,0))="model_only_needs_datasheet"),"VERIFY","PASS")) | M6: Model-only scenario; datasheet values pending.
A7: Growatt hybrid | B7: SPH 10000TL3 BH-UP | C7: JKM575N-72HL4-V | D7: US5000 | E7: 8 | F7: 1 | G7: =ROUND(INDEX(Panels!G:G,MATCH(C7,Panels!C:C,0))*(1+(INDEX(Panels!J:J,MATCH(C7,Panels!C:C,0))/100)*(Inputs!B5-25))*E7,1) | H7: =ROUND(INDEX(Panels!E:E,MATCH(C7,Panels!C:C,0))*(1+(INDEX(Panels!J:J,MATCH(C7,Panels!C:C,0))/100)*(Inputs!B6-25))*E7,1) | I7: =IF(OR(INDEX(Inverters!Q:Q,MATCH(B7,Inverters!C:C,0))="model_only_needs_datasheet",INDEX(Panels!O:O,MATCH(C7,Panels!C:C,0))="model_only_needs_datasheet"),"VERIFY",IF(AND(G7<INDEX(Inverters!G:G,MATCH(B7,Inverters!C:C,0)),H7>=INDEX(Inverters!I:I,MATCH(B7,Inverters!C:C,0)),H7<=INDEX(Inverters!J:J,MATCH(B7,Inverters!C:C,0))),"PASS","FAIL")) | J7: =IF(OR(INDEX(Inverters!Q:Q,MATCH(B7,Inverters!C:C,0))="model_only_needs_datasheet",INDEX(Panels!O:O,MATCH(C7,Panels!C:C,0))="model_only_needs_datasheet"),"VERIFY",IF(INDEX(Panels!F:F,MATCH(C7,Panels!C:C,0))*F7<=INDEX(Inverters!M:M,MATCH(B7,Inverters!C:C,0)),"PASS","FAIL")) | K7: =IF(ISNUMBER(SEARCH("Deye",INDEX(Batteries!M:M,MATCH(D7,Batteries!C:C,0)))),"PASS","VERIFY") | L7: =IF(OR(I7="FAIL",J7="FAIL"),"FAIL",IF(OR(I7="VERIFY",J7="VERIFY",K7="VERIFY",INDEX(Inverters!Q:Q,MATCH(B7,Inverters!C:C,0))="model_only_needs_datasheet",INDEX(Panels!O:O,MATCH(C7,Panels!C:C,0))="model_only_needs_datasheet",INDEX(Batteries!N:N,MATCH(D7,Batteries!C:C,0))="model_only_needs_datasheet"),"VERIFY","PASS")) | M7: Needs datasheet verification for exact Growatt electrical limits.
A8: Solis hybrid | B8: S6-EH3P10K-H-EU | C8: JKM575N-72HL4-V | D8: BX51100 | E8: 8 | F8: 1 | G8: =ROUND(INDEX(Panels!G:G,MATCH(C8,Panels!C:C,0))*(1+(INDEX(Panels!J:J,MATCH(C8,Panels!C:C,0))/100)*(Inputs!B5-25))*E8,1) | H8: =ROUND(INDEX(Panels!E:E,MATCH(C8,Panels!C:C,0))*(1+(INDEX(Panels!J:J,MATCH(C8,Panels!C:C,0))/100)*(Inputs!B6-25))*E8,1) | I8: =IF(OR(INDEX(Inverters!Q:Q,MATCH(B8,Inverters!C:C,0))="model_only_needs_datasheet",INDEX(Panels!O:O,MATCH(C8,Panels!C:C,0))="model_only_needs_datasheet"),"VERIFY",IF(AND(G8<INDEX(Inverters!G:G,MATCH(B8,Inverters!C:C,0)),H8>=INDEX(Inverters!I:I,MATCH(B8,Inverters!C:C,0)),H8<=INDEX(Inverters!J:J,MATCH(B8,Inverters!C:C,0))),"PASS","FAIL")) | J8: =IF(OR(INDEX(Inverters!Q:Q,MATCH(B8,Inverters!C:C,0))="model_only_needs_datasheet",INDEX(Panels!O:O,MATCH(C8,Panels!C:C,0))="model_only_needs_datasheet"),"VERIFY",IF(INDEX(Panels!F:F,MATCH(C8,Panels!C:C,0))*F8<=INDEX(Inverters!M:M,MATCH(B8,Inverters!C:C,0)),"PASS","FAIL")) | K8: =IF(ISNUMBER(SEARCH("Deye",INDEX(Batteries!M:M,MATCH(D8,Batteries!C:C,0)))),"PASS","VERIFY") | L8: =IF(OR(I8="FAIL",J8="FAIL"),"FAIL",IF(OR(I8="VERIFY",J8="VERIFY",K8="VERIFY",INDEX(Inverters!Q:Q,MATCH(B8,Inverters!C:C,0))="model_only_needs_datasheet",INDEX(Panels!O:O,MATCH(C8,Panels!C:C,0))="model_only_needs_datasheet",INDEX(Batteries!N:N,MATCH(D8,Batteries!C:C,0))="model_only_needs_datasheet"),"VERIFY","PASS")) | M8: Needs datasheet verification for exact Solis electrical limits.
A9: MUST hybrid | B9: PV1800 PRO-5.2KW-48V | C9: JKM575N-72HL4-V | D9: US5000 | E9: 4 | F9: 1 | G9: =ROUND(INDEX(Panels!G:G,MATCH(C9,Panels!C:C,0))*(1+(INDEX(Panels!J:J,MATCH(C9,Panels!C:C,0))/100)*(Inputs!B5-25))*E9,1) | H9: =ROUND(INDEX(Panels!E:E,MATCH(C9,Panels!C:C,0))*(1+(INDEX(Panels!J:J,MATCH(C9,Panels!C:C,0))/100)*(Inputs!B6-25))*E9,1) | I9: =IF(OR(INDEX(Inverters!Q:Q,MATCH(B9,Inverters!C:C,0))="model_only_needs_datasheet",INDEX(Panels!O:O,MATCH(C9,Panels!C:C,0))="model_only_needs_datasheet"),"VERIFY",IF(AND(G9<INDEX(Inverters!G:G,MATCH(B9,Inverters!C:C,0)),H9>=INDEX(Inverters!I:I,MATCH(B9,Inverters!C:C,0)),H9<=INDEX(Inverters!J:J,MATCH(B9,Inverters!C:C,0))),"PASS","FAIL")) | J9: =IF(OR(INDEX(Inverters!Q:Q,MATCH(B9,Inverters!C:C,0))="model_only_needs_datasheet",INDEX(Panels!O:O,MATCH(C9,Panels!C:C,0))="model_only_needs_datasheet"),"VERIFY",IF(INDEX(Panels!F:F,MATCH(C9,Panels!C:C,0))*F9<=INDEX(Inverters!M:M,MATCH(B9,Inverters!C:C,0)),"PASS","FAIL")) | K9: =IF(ISNUMBER(SEARCH("Deye",INDEX(Batteries!M:M,MATCH(D9,Batteries!C:C,0)))),"PASS","VERIFY") | L9: =IF(OR(I9="FAIL",J9="FAIL"),"FAIL",IF(OR(I9="VERIFY",J9="VERIFY",K9="VERIFY",INDEX(Inverters!Q:Q,MATCH(B9,Inverters!C:C,0))="model_only_needs_datasheet",INDEX(Panels!O:O,MATCH(C9,Panels!C:C,0))="model_only_needs_datasheet",INDEX(Batteries!N:N,MATCH(D9,Batteries!C:C,0))="model_only_needs_datasheet"),"VERIFY","PASS")) | M9: Low-voltage starter check.

Sheet Economics
A1: Экономика (Economics) | B1: Значение (Value) | C1: Ед. изм. (Unit) | D1: Формула / смысл (Formula / meaning)
A2: Регион / тарифная зона (Region / tariff zone) | B2: =Inputs!B25 | D2: Из листа Inputs (From Inputs)
A3: Мощность выбранной панели (Selected panel power) | B3: =INDEX(Panels!D:D,MATCH(Inputs!B4,Panels!C:C,0)) | C3: W | D3: Из базы Panels (From Panels database)
A4: Total panel count | B4: =Inputs!B12 | C4: pcs | D4: Из листа Inputs (From Inputs)
A5: Мощность СЭС (PV system size) | B5: =B3*B4/1000 | C5: kWp | D5: Panel power x total panels
A6: Удельная выработка (Specific yield) | B6: =INDEX(Regions!B:B,MATCH(B2,Regions!A:A,0)) | C6: kWh/kWp/year | D6: Из базы Regions (From Regions database)
A7: Коэффициент производительности (Performance ratio) | B7: 0.85 | C7: factor | D7: Стартовый коэффициент потерь системы (Starter system loss factor)
A8: Годовая выработка (Annual generation) | B8: =ROUND(B5*B6*B7,0) | C8: kWh/year | D8: Мощность PV x выработка x коэффициент производительности (PV size x yield x performance ratio)
A9: Розничный тариф (Retail tariff) | B9: =INDEX(Tariffs!B:B,MATCH(B2,Tariffs!A:A,0)) | C9: RUB/kWh | D9: Из базы Tariffs (From Tariffs database)
A10: Экспорт / зеленый тариф (Export / green tariff) | B10: =INDEX(Tariffs!C:C,MATCH(B2,Tariffs!A:A,0)) | C10: RUB/kWh | D10: Стартовая цена покупки микрогенерации (Starter microgeneration purchase value)
A11: Доля собственного потребления (Self-consumption share) | B11: =Inputs!B26 | C11: % | D11: Из листа Inputs (From Inputs)
A12: Годовая экономия (Annual savings) | B12: =ROUND(B8*(B11/100)*B9+B8*(1-B11/100)*B10,0) | C12: RUB/year | D12: Self-consumed value plus exported value
A13: Простая окупаемость (Simple payback) | B13: =IF(B12>0,ROUND(B14/B12,1),"") | C13: years | D13: Стоимость системы / годовая экономия (Installed cost / annual savings)
A14: Стоимость установленной системы (Installed system cost) | B14: =Inputs!B27 | C14: RUB | D14: Из листа Inputs (From Inputs)
A15: Статус источника тарифа (Tariff source status) | B15: =Inputs!B28 | D15: VERIFY until supplier/date is checked
A16: Источник розничного тарифа (Retail tariff source) | B16: =INDEX(Tariffs!D:D,MATCH(B2,Tariffs!A:A,0)) | D16: URL источника (Source URL)
A17: Источник экспортного тарифа (Export tariff source) | B17: =INDEX(Tariffs!E:E,MATCH(B2,Tariffs!A:A,0)) | D17: URL источника (Source URL)
A18: Потребление в месяц (Monthly consumption) | B18: =Inputs!B29 | C18: kWh/month | D18: Из листа Inputs (From Inputs)
A19: Годовое потребление (Annual consumption) | B19: =B18*12 | C19: kWh/year | D19: Месячное потребление x 12 (Monthly consumption x 12)
A20: Целевое годовое покрытие (Target annual coverage) | B20: =B19*Inputs!B30/100 | C20: kWh/year | D20: Годовое потребление x целевое покрытие (Annual consumption x target coverage)
A21: Смешанный тариф день-ночь (Day-night blended tariff) | B21: =Inputs!B33*(Inputs!B32/100)+Inputs!B34*(1-Inputs!B32/100) | C21: RUB/kWh | D21: Доля дня x дневной тариф плюс доля ночи x ночной тариф (Day share x day tariff plus night share x night tariff)
A22: Оценочная текущая годовая стоимость (Estimated current annual cost) | B22: =B19*B9 | C22: RUB/year | D22: Годовое потребление x розничный тариф (Annual consumption x retail tariff)
A23: Оценочная годовая стоимость день-ночь (Estimated day-night annual cost) | B23: =B19*B21 | C23: RUB/year | D23: Годовое потребление x смешанный тариф день-ночь (Annual consumption x blended day-night tariff)
A24: Потенциальная экономия день-ночь до СЭС (Potential day-night saving before PV) | B24: =MAX(0,B22-B23) | C24: RUB/year | D24: Текущая стоимость минус стоимость день-ночь (Current cost minus day-night cost)

Sheet SystemOptions
A1: Вариант (Option) | B1: Качество (Quality) | C1: Стоимость за кВтп (Cost per kWp) | D1: Срок службы (Service life) | E1: Деградация (Degradation) | F1: Требуемая годовая выработка (Required annual generation) | G1: Требуемая мощность кВтп (Required kWp) | H1: Рекомендуемая мощность кВтп (Recommended kWp) | I1: Панели (Panels) | J1: Дневная выработка (Daily generation) | K1: Месячная выработка (Monthly generation) | L1: Годовая выработка (Annual generation) | M1: Покрытие (Coverage) | N1: Оценочная стоимость (Estimated cost) | O1: Экономия на едином тарифе (Single-rate savings) | P1: Экономия день-ночь (Day-night savings) | Q1: Выручка от зеленого тарифа (Green tariff export revenue) | R1: Окупаемость день-ночь (Payback day-night) | S1: Примечания (Notes)
A2: Premium | B2: =INDEX(OptionTiers!B:B,MATCH(A2,OptionTiers!A:A,0)) | C2: =INDEX(OptionTiers!C:C,MATCH(A2,OptionTiers!A:A,0)) | D2: =INDEX(OptionTiers!D:D,MATCH(A2,OptionTiers!A:A,0)) | E2: =INDEX(OptionTiers!E:E,MATCH(A2,OptionTiers!A:A,0)) | F2: =Economics!B20 | G2: =F2/Economics!B6/Economics!B7 | H2: =ROUNDUP(G2*1000/INDEX(Panels!D:D,MATCH(Inputs!B4,Panels!C:C,0)),0)*INDEX(Panels!D:D,MATCH(Inputs!B4,Panels!C:C,0))/1000 | I2: =ROUNDUP(G2*1000/INDEX(Panels!D:D,MATCH(Inputs!B4,Panels!C:C,0)),0) | J2: =ROUND(L2/365,1) | K2: =ROUND(L2/12,0) | L2: =ROUND(H2*Economics!B6*Economics!B7,0) | M2: =ROUND(L2/Economics!B19*100,0) | N2: =ROUND(H2*C2,0) | O2: =ROUND(L2*(Inputs!B26/100)*Economics!B9+L2*(1-Inputs!B26/100)*Economics!B10,0) | P2: =ROUND(L2*(Inputs!B26/100)*Economics!B21+L2*(1-Inputs!B26/100)*Economics!B10+Economics!B24,0) | Q2: =ROUND(L2*(1-Inputs!B26/100)*Economics!B10,0) | R2: =IF(P2>0,ROUND(N2/P2,1),"") | S2: Повышенный бюджет; сверить коммерческое предложение (Higher allowance; verify commercial offer)
A3: Standard | B3: =INDEX(OptionTiers!B:B,MATCH(A3,OptionTiers!A:A,0)) | C3: =INDEX(OptionTiers!C:C,MATCH(A3,OptionTiers!A:A,0)) | D3: =INDEX(OptionTiers!D:D,MATCH(A3,OptionTiers!A:A,0)) | E3: =INDEX(OptionTiers!E:E,MATCH(A3,OptionTiers!A:A,0)) | F3: =Economics!B20 | G3: =F3/Economics!B6/Economics!B7 | H3: =ROUNDUP(G3*1000/INDEX(Panels!D:D,MATCH(Inputs!B4,Panels!C:C,0)),0)*INDEX(Panels!D:D,MATCH(Inputs!B4,Panels!C:C,0))/1000 | I3: =ROUNDUP(G3*1000/INDEX(Panels!D:D,MATCH(Inputs!B4,Panels!C:C,0)),0) | J3: =ROUND(L3/365,1) | K3: =ROUND(L3/12,0) | L3: =ROUND(H3*Economics!B6*Economics!B7,0) | M3: =ROUND(L3/Economics!B19*100,0) | N3: =ROUND(H3*C3,0) | O3: =ROUND(L3*(Inputs!B26/100)*Economics!B9+L3*(1-Inputs!B26/100)*Economics!B10,0) | P3: =ROUND(L3*(Inputs!B26/100)*Economics!B21+L3*(1-Inputs!B26/100)*Economics!B10+Economics!B24,0) | Q3: =ROUND(L3*(1-Inputs!B26/100)*Economics!B10,0) | R3: =IF(P3>0,ROUND(N3/P3,1),"") | S3: Сбалансированный вариант по умолчанию (Balanced default option)
A4: Economy | B4: =INDEX(OptionTiers!B:B,MATCH(A4,OptionTiers!A:A,0)) | C4: =INDEX(OptionTiers!C:C,MATCH(A4,OptionTiers!A:A,0)) | D4: =INDEX(OptionTiers!D:D,MATCH(A4,OptionTiers!A:A,0)) | E4: =INDEX(OptionTiers!E:E,MATCH(A4,OptionTiers!A:A,0)) | F4: =Economics!B20 | G4: =F4/Economics!B6/Economics!B7 | H4: =ROUNDUP(G4*1000/INDEX(Panels!D:D,MATCH(Inputs!B4,Panels!C:C,0)),0)*INDEX(Panels!D:D,MATCH(Inputs!B4,Panels!C:C,0))/1000 | I4: =ROUNDUP(G4*1000/INDEX(Panels!D:D,MATCH(Inputs!B4,Panels!C:C,0)),0) | J4: =ROUND(L4/365,1) | K4: =ROUND(L4/12,0) | L4: =ROUND(H4*Economics!B6*Economics!B7,0) | M4: =ROUND(L4/Economics!B19*100,0) | N4: =ROUND(H4*C4,0) | O4: =ROUND(L4*(Inputs!B26/100)*Economics!B9+L4*(1-Inputs!B26/100)*Economics!B10,0) | P4: =ROUND(L4*(Inputs!B26/100)*Economics!B21+L4*(1-Inputs!B26/100)*Economics!B10+Economics!B24,0) | Q4: =ROUND(L4*(1-Inputs!B26/100)*Economics!B10,0) | R4: =IF(P4>0,ROUND(N4/P4,1),"") | S4: Пониженный бюджет; проверить гарантии (Lower cost allowance; verify warranties)

Sheet Lifetime
A1: Год (Year) | B1: Выработка Premium (Premium generation) | C1: Выработка Standard (Standard generation) | D1: Выработка Economy (Economy generation) | E1: Накопительно Premium (Premium cumulative) | F1: Накопительно Standard (Standard cumulative) | G1: Накопительно Economy (Economy cumulative)
A2: 0 | B2: =ROUND(SystemOptions!L2*(1-SystemOptions!E2/100)^A2,0) | C2: =ROUND(SystemOptions!L3*(1-SystemOptions!E3/100)^A2,0) | D2: =ROUND(SystemOptions!L4*(1-SystemOptions!E4/100)^A2,0) | E2: =SUM(B$2:B2) | F2: =SUM(C$2:C2) | G2: =SUM(D$2:D2)
A3: 1 | B3: =ROUND(SystemOptions!L2*(1-SystemOptions!E2/100)^A3,0) | C3: =ROUND(SystemOptions!L3*(1-SystemOptions!E3/100)^A3,0) | D3: =ROUND(SystemOptions!L4*(1-SystemOptions!E4/100)^A3,0) | E3: =SUM(B$2:B3) | F3: =SUM(C$2:C3) | G3: =SUM(D$2:D3)
A4: 2 | B4: =ROUND(SystemOptions!L2*(1-SystemOptions!E2/100)^A4,0) | C4: =ROUND(SystemOptions!L3*(1-SystemOptions!E3/100)^A4,0) | D4: =ROUND(SystemOptions!L4*(1-SystemOptions!E4/100)^A4,0) | E4: =SUM(B$2:B4) | F4: =SUM(C$2:C4) | G4: =SUM(D$2:D4)
A5: 3 | B5: =ROUND(SystemOptions!L2*(1-SystemOptions!E2/100)^A5,0) | C5: =ROUND(SystemOptions!L3*(1-SystemOptions!E3/100)^A5,0) | D5: =ROUND(SystemOptions!L4*(1-SystemOptions!E4/100)^A5,0) | E5: =SUM(B$2:B5) | F5: =SUM(C$2:C5) | G5: =SUM(D$2:D5)
A6: 4 | B6: =ROUND(SystemOptions!L2*(1-SystemOptions!E2/100)^A6,0) | C6: =ROUND(SystemOptions!L3*(1-SystemOptions!E3/100)^A6,0) | D6: =ROUND(SystemOptions!L4*(1-SystemOptions!E4/100)^A6,0) | E6: =SUM(B$2:B6) | F6: =SUM(C$2:C6) | G6: =SUM(D$2:D6)
A7: 5 | B7: =ROUND(SystemOptions!L2*(1-SystemOptions!E2/100)^A7,0) | C7: =ROUND(SystemOptions!L3*(1-SystemOptions!E3/100)^A7,0) | D7: =ROUND(SystemOptions!L4*(1-SystemOptions!E4/100)^A7,0) | E7: =SUM(B$2:B7) | F7: =SUM(C$2:C7) | G7: =SUM(D$2:D7)
A8: 6 | B8: =ROUND(SystemOptions!L2*(1-SystemOptions!E2/100)^A8,0) | C8: =ROUND(SystemOptions!L3*(1-SystemOptions!E3/100)^A8,0) | D8: =ROUND(SystemOptions!L4*(1-SystemOptions!E4/100)^A8,0) | E8: =SUM(B$2:B8) | F8: =SUM(C$2:C8) | G8: =SUM(D$2:D8)
A9: 7 | B9: =ROUND(SystemOptions!L2*(1-SystemOptions!E2/100)^A9,0) | C9: =ROUND(SystemOptions!L3*(1-SystemOptions!E3/100)^A9,0) | D9: =ROUND(SystemOptions!L4*(1-SystemOptions!E4/100)^A9,0) | E9: =SUM(B$2:B9) | F9: =SUM(C$2:C9) | G9: =SUM(D$2:D9)
A10: 8 | B10: =ROUND(SystemOptions!L2*(1-SystemOptions!E2/100)^A10,0) | C10: =ROUND(SystemOptions!L3*(1-SystemOptions!E3/100)^A10,0) | D10: =ROUND(SystemOptions!L4*(1-SystemOptions!E4/100)^A10,0) | E10: =SUM(B$2:B10) | F10: =SUM(C$2:C10) | G10: =SUM(D$2:D10)
A11: 9 | B11: =ROUND(SystemOptions!L2*(1-SystemOptions!E2/100)^A11,0) | C11: =ROUND(SystemOptions!L3*(1-SystemOptions!E3/100)^A11,0) | D11: =ROUND(SystemOptions!L4*(1-SystemOptions!E4/100)^A11,0) | E11: =SUM(B$2:B11) | F11: =SUM(C$2:C11) | G11: =SUM(D$2:D11)
A12: 10 | B12: =ROUND(SystemOptions!L2*(1-SystemOptions!E2/100)^A12,0) | C12: =ROUND(SystemOptions!L3*(1-SystemOptions!E3/100)^A12,0) | D12: =ROUND(SystemOptions!L4*(1-SystemOptions!E4/100)^A12,0) | E12: =SUM(B$2:B12) | F12: =SUM(C$2:C12) | G12: =SUM(D$2:D12)
A13: 11 | B13: =ROUND(SystemOptions!L2*(1-SystemOptions!E2/100)^A13,0) | C13: =ROUND(SystemOptions!L3*(1-SystemOptions!E3/100)^A13,0) | D13: =ROUND(SystemOptions!L4*(1-SystemOptions!E4/100)^A13,0) | E13: =SUM(B$2:B13) | F13: =SUM(C$2:C13) | G13: =SUM(D$2:D13)
A14: 12 | B14: =ROUND(SystemOptions!L2*(1-SystemOptions!E2/100)^A14,0) | C14: =ROUND(SystemOptions!L3*(1-SystemOptions!E3/100)^A14,0) | D14: =ROUND(SystemOptions!L4*(1-SystemOptions!E4/100)^A14,0) | E14: =SUM(B$2:B14) | F14: =SUM(C$2:C14) | G14: =SUM(D$2:D14)
A15: 13 | B15: =ROUND(SystemOptions!L2*(1-SystemOptions!E2/100)^A15,0) | C15: =ROUND(SystemOptions!L3*(1-SystemOptions!E3/100)^A15,0) | D15: =ROUND(SystemOptions!L4*(1-SystemOptions!E4/100)^A15,0) | E15: =SUM(B$2:B15) | F15: =SUM(C$2:C15) | G15: =SUM(D$2:D15)
A16: 14 | B16: =ROUND(SystemOptions!L2*(1-SystemOptions!E2/100)^A16,0) | C16: =ROUND(SystemOptions!L3*(1-SystemOptions!E3/100)^A16,0) | D16: =ROUND(SystemOptions!L4*(1-SystemOptions!E4/100)^A16,0) | E16: =SUM(B$2:B16) | F16: =SUM(C$2:C16) | G16: =SUM(D$2:D16)
A17: 15 | B17: =ROUND(SystemOptions!L2*(1-SystemOptions!E2/100)^A17,0) | C17: =ROUND(SystemOptions!L3*(1-SystemOptions!E3/100)^A17,0) | D17: =ROUND(SystemOptions!L4*(1-SystemOptions!E4/100)^A17,0) | E17: =SUM(B$2:B17) | F17: =SUM(C$2:C17) | G17: =SUM(D$2:D17)
A18: 16 | B18: =ROUND(SystemOptions!L2*(1-SystemOptions!E2/100)^A18,0) | C18: =ROUND(SystemOptions!L3*(1-SystemOptions!E3/100)^A18,0) | D18: =ROUND(SystemOptions!L4*(1-SystemOptions!E4/100)^A18,0) | E18: =SUM(B$2:B18) | F18: =SUM(C$2:C18) | G18: =SUM(D$2:D18)
A19: 17 | B19: =ROUND(SystemOptions!L2*(1-SystemOptions!E2/100)^A19,0) | C19: =ROUND(SystemOptions!L3*(1-SystemOptions!E3/100)^A19,0) | D19: =ROUND(SystemOptions!L4*(1-SystemOptions!E4/100)^A19,0) | E19: =SUM(B$2:B19) | F19: =SUM(C$2:C19) | G19: =SUM(D$2:D19)
A20: 18 | B20: =ROUND(SystemOptions!L2*(1-SystemOptions!E2/100)^A20,0) | C20: =ROUND(SystemOptions!L3*(1-SystemOptions!E3/100)^A20,0) | D20: =ROUND(SystemOptions!L4*(1-SystemOptions!E4/100)^A20,0) | E20: =SUM(B$2:B20) | F20: =SUM(C$2:C20) | G20: =SUM(D$2:D20)
A21: 19 | B21: =ROUND(SystemOptions!L2*(1-SystemOptions!E2/100)^A21,0) | C21: =ROUND(SystemOptions!L3*(1-SystemOptions!E3/100)^A21,0) | D21: =ROUND(SystemOptions!L4*(1-SystemOptions!E4/100)^A21,0) | E21: =SUM(B$2:B21) | F21: =SUM(C$2:C21) | G21: =SUM(D$2:D21)
A22: 20 | B22: =ROUND(SystemOptions!L2*(1-SystemOptions!E2/100)^A22,0) | C22: =ROUND(SystemOptions!L3*(1-SystemOptions!E3/100)^A22,0) | D22: =ROUND(SystemOptions!L4*(1-SystemOptions!E4/100)^A22,0) | E22: =SUM(B$2:B22) | F22: =SUM(C$2:C22) | G22: =SUM(D$2:D22)

Sheet OptionTiers
A1: tier | B1: quality_level | C1: cost_rub_per_kwp | D1: panel_service_life_years | E1: panel_degradation_pct_year | F1: notes
A2: Premium | B2: premium | C2: 105000 | D2: 25 | E2: 0.4 | F2: Higher equipment and installation allowance; verify commercial offer.
A3: Standard | B3: base | C3: 85000 | D3: 25 | E3: 0.5 | F3: Balanced default option for most customers; verify commercial offer.
A4: Economy | B4: economy | C4: 70000 | D4: 20 | E4: 0.7 | F4: Lower cost allowance; verify component quality and warranty.

Sheet MonthlyGeneration
A1: Месяц (Month) | B1: Выработка (Generation) | C1: Потребление (Consumption) | D1: Собственное потребление (Self-consumed) | E1: Стоимость собственного потребления (Self-consumption value) | F1: Экспортировано (Exported) | G1: Стоимость экспорта (Export value) | H1: Общая стоимость (Total value) | I1: Покрытие (Coverage)
A2: Янв (Jan) | B2: =ROUND(SystemOptions!L3*INDEX(MonthlyYieldProfile!B:B,MATCH(Inputs!B25,MonthlyYieldProfile!A:A,0))/100,0) | C2: =Inputs!B29 | D2: =MIN(B2,C2,B2*Inputs!B26/100) | E2: =ROUND(D2*Economics!B21,0) | F2: =MAX(0,B2-D2) | G2: =ROUND(F2*Economics!B10,0) | H2: =E2+G2 | I2: =ROUND(B2/C2*100,0)
A3: Фев (Feb) | B3: =ROUND(SystemOptions!L3*INDEX(MonthlyYieldProfile!C:C,MATCH(Inputs!B25,MonthlyYieldProfile!A:A,0))/100,0) | C3: =Inputs!B29 | D3: =MIN(B3,C3,B3*Inputs!B26/100) | E3: =ROUND(D3*Economics!B21,0) | F3: =MAX(0,B3-D3) | G3: =ROUND(F3*Economics!B10,0) | H3: =E3+G3 | I3: =ROUND(B3/C3*100,0)
A4: Мар (Mar) | B4: =ROUND(SystemOptions!L3*INDEX(MonthlyYieldProfile!D:D,MATCH(Inputs!B25,MonthlyYieldProfile!A:A,0))/100,0) | C4: =Inputs!B29 | D4: =MIN(B4,C4,B4*Inputs!B26/100) | E4: =ROUND(D4*Economics!B21,0) | F4: =MAX(0,B4-D4) | G4: =ROUND(F4*Economics!B10,0) | H4: =E4+G4 | I4: =ROUND(B4/C4*100,0)
A5: Апр (Apr) | B5: =ROUND(SystemOptions!L3*INDEX(MonthlyYieldProfile!E:E,MATCH(Inputs!B25,MonthlyYieldProfile!A:A,0))/100,0) | C5: =Inputs!B29 | D5: =MIN(B5,C5,B5*Inputs!B26/100) | E5: =ROUND(D5*Economics!B21,0) | F5: =MAX(0,B5-D5) | G5: =ROUND(F5*Economics!B10,0) | H5: =E5+G5 | I5: =ROUND(B5/C5*100,0)
A6: Май (May) | B6: =ROUND(SystemOptions!L3*INDEX(MonthlyYieldProfile!F:F,MATCH(Inputs!B25,MonthlyYieldProfile!A:A,0))/100,0) | C6: =Inputs!B29 | D6: =MIN(B6,C6,B6*Inputs!B26/100) | E6: =ROUND(D6*Economics!B21,0) | F6: =MAX(0,B6-D6) | G6: =ROUND(F6*Economics!B10,0) | H6: =E6+G6 | I6: =ROUND(B6/C6*100,0)
A7: Июн (Jun) | B7: =ROUND(SystemOptions!L3*INDEX(MonthlyYieldProfile!G:G,MATCH(Inputs!B25,MonthlyYieldProfile!A:A,0))/100,0) | C7: =Inputs!B29 | D7: =MIN(B7,C7,B7*Inputs!B26/100) | E7: =ROUND(D7*Economics!B21,0) | F7: =MAX(0,B7-D7) | G7: =ROUND(F7*Economics!B10,0) | H7: =E7+G7 | I7: =ROUND(B7/C7*100,0)
A8: Июл (Jul) | B8: =ROUND(SystemOptions!L3*INDEX(MonthlyYieldProfile!H:H,MATCH(Inputs!B25,MonthlyYieldProfile!A:A,0))/100,0) | C8: =Inputs!B29 | D8: =MIN(B8,C8,B8*Inputs!B26/100) | E8: =ROUND(D8*Economics!B21,0) | F8: =MAX(0,B8-D8) | G8: =ROUND(F8*Economics!B10,0) | H8: =E8+G8 | I8: =ROUND(B8/C8*100,0)
A9: Авг (Aug) | B9: =ROUND(SystemOptions!L3*INDEX(MonthlyYieldProfile!I:I,MATCH(Inputs!B25,MonthlyYieldProfile!A:A,0))/100,0) | C9: =Inputs!B29 | D9: =MIN(B9,C9,B9*Inputs!B26/100) | E9: =ROUND(D9*Economics!B21,0) | F9: =MAX(0,B9-D9) | G9: =ROUND(F9*Economics!B10,0) | H9: =E9+G9 | I9: =ROUND(B9/C9*100,0)
A10: Сен (Sep) | B10: =ROUND(SystemOptions!L3*INDEX(MonthlyYieldProfile!J:J,MATCH(Inputs!B25,MonthlyYieldProfile!A:A,0))/100,0) | C10: =Inputs!B29 | D10: =MIN(B10,C10,B10*Inputs!B26/100) | E10: =ROUND(D10*Economics!B21,0) | F10: =MAX(0,B10-D10) | G10: =ROUND(F10*Economics!B10,0) | H10: =E10+G10 | I10: =ROUND(B10/C10*100,0)
A11: Окт (Oct) | B11: =ROUND(SystemOptions!L3*INDEX(MonthlyYieldProfile!K:K,MATCH(Inputs!B25,MonthlyYieldProfile!A:A,0))/100,0) | C11: =Inputs!B29 | D11: =MIN(B11,C11,B11*Inputs!B26/100) | E11: =ROUND(D11*Economics!B21,0) | F11: =MAX(0,B11-D11) | G11: =ROUND(F11*Economics!B10,0) | H11: =E11+G11 | I11: =ROUND(B11/C11*100,0)
A12: Ноя (Nov) | B12: =ROUND(SystemOptions!L3*INDEX(MonthlyYieldProfile!L:L,MATCH(Inputs!B25,MonthlyYieldProfile!A:A,0))/100,0) | C12: =Inputs!B29 | D12: =MIN(B12,C12,B12*Inputs!B26/100) | E12: =ROUND(D12*Economics!B21,0) | F12: =MAX(0,B12-D12) | G12: =ROUND(F12*Economics!B10,0) | H12: =E12+G12 | I12: =ROUND(B12/C12*100,0)
A13: Дек (Dec) | B13: =ROUND(SystemOptions!L3*INDEX(MonthlyYieldProfile!M:M,MATCH(Inputs!B25,MonthlyYieldProfile!A:A,0))/100,0) | C13: =Inputs!B29 | D13: =MIN(B13,C13,B13*Inputs!B26/100) | E13: =ROUND(D13*Economics!B21,0) | F13: =MAX(0,B13-D13) | G13: =ROUND(F13*Economics!B10,0) | H13: =E13+G13 | I13: =ROUND(B13/C13*100,0)
A14: Итого (Total) | B14: =SUM(B2:B13) | C14: =SUM(C2:C13) | D14: =SUM(D2:D13) | E14: =SUM(E2:E13) | F14: =SUM(F2:F13) | G14: =SUM(G2:G13) | H14: =SUM(H2:H13) | I14: =ROUND(B14/C14*100,0)

Sheet MonthlyYieldProfile
A1: region | B1: jan_pct | C1: feb_pct | D1: mar_pct | E1: apr_pct | F1: may_pct | G1: jun_pct | H1: jul_pct | I1: aug_pct | J1: sep_pct | K1: oct_pct | L1: nov_pct | M1: dec_pct | N1: data_status | O1: notes
A2: Moscow starter | B2: 3 | C2: 5 | D2: 8 | E2: 11 | F2: 13 | G2: 14 | H2: 14 | I2: 12 | J2: 9 | K2: 6 | L2: 3 | M2: 2 | N2: seed_verify_source | O2: Starter seasonal split; verify exact site with PVGIS or Global Solar Atlas.
A3: Saint Petersburg starter | B3: 2 | C3: 4 | D3: 8 | E3: 11 | F3: 14 | G3: 15 | H3: 15 | I3: 12 | J3: 9 | K3: 5 | L3: 3 | M3: 2 | N3: seed_verify_source | O3: Starter seasonal split; verify exact site with PVGIS or Global Solar Atlas.
A4: Krasnodar starter | B4: 5 | C4: 6 | D4: 9 | E4: 10 | F4: 12 | G4: 13 | H4: 13 | I4: 12 | J4: 9 | K4: 6 | L4: 4 | M4: 3 | N4: seed_verify_source | O4: Starter seasonal split; verify exact site with PVGIS or Global Solar Atlas.
A5: Rostov-on-Don starter | B5: 4 | C5: 6 | D5: 9 | E5: 11 | F5: 12 | G5: 13 | H5: 13 | I5: 12 | J5: 9 | K5: 6 | L5: 3 | M5: 2 | N5: seed_verify_source | O5: Starter seasonal split; verify exact site with PVGIS or Global Solar Atlas.
A6: Yekaterinburg starter | B6: 3 | C6: 5 | D6: 9 | E6: 11 | F6: 13 | G6: 14 | H6: 14 | I6: 11 | J6: 9 | K6: 6 | L6: 3 | M6: 2 | N6: seed_verify_source | O6: Starter seasonal split; verify exact site with PVGIS or Global Solar Atlas.

Sheet CableSizing
A1: section_mm2 | B1: ampacity_a | C1: notes
A2: 1.5 | B2: 0 | C2: Lookup floor for low-current auxiliary AC circuits; verify installation method.
A3: 2.5 | B3: 25 | C3: Starter copper cable ampacity assumption; verify installation method.
A4: 4 | B4: 35 | C4: Starter copper cable ampacity assumption; verify installation method.
A5: 6 | B5: 50 | C5: Starter copper cable ampacity assumption; verify installation method.
A6: 10 | B6: 70 | C6: Starter copper cable ampacity assumption; verify installation method.
A7: 16 | B7: 90 | C7: Starter copper cable ampacity assumption; verify installation method.
A8: 25 | B8: 120 | C8: Starter copper cable ampacity assumption; verify installation method.
A9: 35 | B9: 150 | C9: Starter copper cable ampacity assumption; verify installation method.
A10: 50 | B10: 180 | C10: Starter copper cable ampacity assumption; verify installation method.
A11: 70 | B11: 230 | C11: Starter copper cable ampacity assumption; verify installation method.
A12: 95 | B12: 280 | C12: Starter copper cable ampacity assumption; verify installation method.
A13: 120 | B13: 330 | C13: Starter copper cable ampacity assumption; verify installation method.

Sheet ProtectionRules
A1: section_mm2 | B1: ampacity_a | C1: notes
A2: 1.5 | B2: 0 | C2: Lookup floor for low-current auxiliary AC circuits; verify installation method.
A3: 2.5 | B3: 25 | C3: Starter copper cable ampacity assumption; verify installation method.
A4: 4 | B4: 35 | C4: Starter copper cable ampacity assumption; verify installation method.
A5: 6 | B5: 50 | C5: Starter copper cable ampacity assumption; verify installation method.
A6: 10 | B6: 70 | C6: Starter copper cable ampacity assumption; verify installation method.
A7: 16 | B7: 90 | C7: Starter copper cable ampacity assumption; verify installation method.
A8: 25 | B8: 120 | C8: Starter copper cable ampacity assumption; verify installation method.
A9: 35 | B9: 150 | C9: Starter copper cable ampacity assumption; verify installation method.
A10: 50 | B10: 180 | C10: Starter copper cable ampacity assumption; verify installation method.
A11: 70 | B11: 230 | C11: Starter copper cable ampacity assumption; verify installation method.
A12: 95 | B12: 280 | C12: Starter copper cable ampacity assumption; verify installation method.
A13: 120 | B13: 330 | C13: Starter copper cable ampacity assumption; verify installation method.
A14: PV cable red | B14: DC cable | C14: 0 | D14: m | E14: user_input | F14: Positive DC cable length; user-defined route length.
A15: PV cable black | B15: DC cable | C15: 0 | D15: m | E15: user_input | F15: Negative DC cable length; user-defined route length.
A16: PE cable | B16: Grounding cable | C16: 0 | D16: m | E16: user_input | F16: Protective earth cable length; user-defined route length.
A17: DC string fuse | B17: DC protection | C17: 0 | D17: pcs | E17: strings_per_mppt_gt_1 | F17: Use when parallel strings are connected; verify by module Isc and local rules.
A18: DC isolator | B18: DC protection | C18: 1 | D18: pcs | E18: one_per_inverter | F18: DC isolator or switch-disconnector; verify inverter built-in equipment.
A19: DC SPD Type 2 | B19: DC protection | C19: 1 | D19: pcs | E19: one_per_array | F19: DC surge protection starter assumption.
A20: AC breaker | B20: AC protection | C20: 1 | D20: pcs | E20: one_per_inverter | F20: AC breaker rating must be selected by inverter output current and local rules.
A21: AC SPD Type 2 | B21: AC protection | C21: 1 | D21: pcs | E21: one_per_system | F21: AC surge protection starter assumption.
A22: AC cable | B22: AC cable | C22: 0 | D22: m | E22: user_input | F22: AC cable length; user-defined route length.
A23: Battery DC cable pair | B23: Battery cable | C23: 1 | D23: pair | E23: one_per_battery_stack | F23: Battery cable pair starter assumption.
A24: Battery fuse or breaker | B24: Battery protection | C24: 1 | D24: pcs | E24: one_per_battery_stack | F24: Battery protection must be selected by battery/inverter current.

Sheet SpdRules
A1: condition | B1: recommended_spd | C1: notes
A2: No external LPS | B2: Type 2 DC/AC SPD | C2: Starter residential/commercial assumption; verify risk assessment and local standards.
A3: External LPS | B3: Type 1+2 DC/AC SPD | C3: Use when building has external lightning protection system; verify coordination.
A4: Overhead supply | B4: Type 1+2 AC SPD | C4: Often required on AC side with overhead supply; verify utility and standards.
A5: Long outdoor DC route | B5: Type 2 DC SPD near inverter and array | C5: May require additional SPD placement; verify cable route and inverter manual.

Sheet EarthingRules
A1: earthing_system | B1: starter_requirement | C1: notes
A2: TN-S | B2: PE continuity and bonding check | C2: Verify PE conductor sizing | D2: equipotential bonding | E2: and SPD connection length.
A3: TN-C-S | B3: Separate PEN/PE handling check | C3: Verify local rules for PV connection | D3: bonding | E3: and SPD earthing.
A4: TT | B4: RCD and earth electrode check | C4: Verify electrode resistance | D4: RCD coordination | E4: and SPD discharge path.
A5: IT | B5: Special protection study required | C5: Do not use starter assumptions without engineering verification.

Sheet CableDerating
A1: factor_type | B1: option | C1: default_factor | D1: notes
A2: installation_method | B2: Open air | C2: 1 | D2: Starter assumption for ventilated cable routes; verify local tables.
A3: installation_method | B3: Conduit or trunking | C3: 0.85 | D3: Starter derating for enclosed routes; verify local tables.
A4: installation_method | B4: Thermal insulation | C4: 0.65 | D4: High derating risk; verify local tables.
A5: grouping | B5: Single circuit | C5: 1 | D5: No grouping derating applied.
A6: grouping | B6: Several circuits | C6: 0.8 | D6: Starter grouping derating; verify actual routing.
A7: temperature | B7: Standard ambient | C7: 1 | D7: Starter assumption.
A8: temperature | B8: High ambient | C8: 0.87 | D8: Starter derating for hot environments; verify cable rating.

Sheet MountingRules
A1: roof_type | B1: component | C1: base_qty | D1: qty_per_panel | E1: qty_per_row | F1: qty_per_joint | G1: qty_per_string | H1: qty_per_array | I1: rounding_unit | J1: notes
A2: Metal tile | B2: Roof hook | C2: 0 | D2: 4 | E2: 0 | F2: 0 | G2: 0 | H2: 0 | I2: 1 | J2: Use 4 hooks per panel as starter assumption; verify by rail span and wind zone.
A3: Metal tile | B3: Rail | C3: 0 | D3: 2 | E3: 0 | F3: 0 | G3: 0 | H3: 0 | I3: 1 | J3: Two rails per panel row equivalent; final length depends on module width and rail stock length.
A4: Metal tile | B4: Rail connector | C4: 0 | D4: 0 | E4: 0 | F4: 2 | G4: 0 | H4: 0 | I4: 1 | J4: Two connectors per rail joint.
A5: Metal tile | B5: End clamp | C5: 0 | D5: 0 | E5: 4 | F5: 0 | G5: 0 | H5: 0 | I5: 1 | J5: Four end clamps per row.
A6: Metal tile | B6: Middle clamp | C6: 0 | D6: 2 | E6: 0 | F6: 0 | G6: 0 | H6: 0 | I6: 1 | J6: Two middle clamps per gap between adjacent panels; formula handles gaps.
A7: Metal tile | B7: Bolt set | C7: 0 | D7: 4 | E7: 0 | F7: 0 | G7: 0 | H7: 0 | I7: 1 | J7: Starter one bolt set per hook.
A8: Metal tile | B8: Grounding clip | C8: 0 | D8: 1 | E8: 0 | F8: 0 | G8: 0 | H8: 0 | I8: 1 | J8: One grounding clip per module.
A9: Metal tile | B9: Cable clip | C9: 0 | D9: 2 | E9: 0 | F9: 0 | G9: 0 | H9: 0 | I9: 1 | J9: Two cable clips per module.
A10: Standing seam | B10: Mini rail clamp | C10: 0 | D10: 4 | E10: 0 | F10: 0 | G10: 0 | H10: 0 | I10: 1 | J10: Use seam clamps or mini-rail clamps; verify seam spacing and clamp approval.
A11: Standing seam | B11: Mini rail | C11: 0 | D11: 2 | E11: 0 | F11: 0 | G11: 0 | H11: 0 | I11: 1 | J11: Two mini-rail supports per module as starter assumption.
A12: Standing seam | B12: Rail connector | C12: 0 | D12: 0 | E12: 0 | F12: 2 | G12: 0 | H12: 0 | I12: 1 | J12: Only used when continuous rail is selected.
A13: Standing seam | B13: End clamp | C13: 0 | D13: 0 | E13: 4 | F13: 0 | G13: 0 | H13: 0 | I13: 1 | J13: Four end clamps per row.
... A41: Ground mount | B41: Cable clip | C41: 0 | D41: 2 | E41: 0 | F41: 0 | G41: 0 | H41: 0 | I41: 1 | J41: Two cable clips per module.

Sheet Regions
A1: region | B1: specific_yield_kwh_per_kwp_year | C1: source_url | D1: data_status | E1: notes
A2: Moscow starter | B2: 950 | C2: https://globalsolaratlas.info/ | D2: seed_verify_source | E2: Starter annual yield assumption; verify exact site with PVGIS or Global Solar Atlas.
A3: Saint Petersburg starter | B3: 850 | C3: https://globalsolaratlas.info/ | D3: seed_verify_source | E3: Starter annual yield assumption; verify exact site with PVGIS or Global Solar Atlas.
A4: Krasnodar starter | B4: 1300 | C4: https://globalsolaratlas.info/ | D4: seed_verify_source | E4: Starter annual yield assumption; verify exact site with PVGIS or Global Solar Atlas.
A5: Rostov-on-Don starter | B5: 1250 | C5: https://globalsolaratlas.info/ | D5: seed_verify_source | E5: Starter annual yield assumption; verify exact site with PVGIS or Global Solar Atlas.
A6: Yekaterinburg starter | B6: 1050 | C6: https://globalsolaratlas.info/ | D6: seed_verify_source | E6: Starter annual yield assumption; verify exact site with PVGIS or Global Solar Atlas.

Sheet Tariffs
A1: region | B1: retail_tariff_rub_kwh | C1: export_tariff_rub_kwh | D1: retail_source_url | E1: export_source_url | F1: data_status | G1: notes
A2: Moscow starter | B2: 8.5 | C2: 3.5 | D2: https://www.mosenergosbyt.ru/ | E2: https://www.atsenergo.ru/ | F2: seed_verify_source | G2: Retail tariff: verify with regional supplier/regulator. Export price: verify through ATS market-price data used for microgeneration surplus purchase.
A3: Saint Petersburg starter | B3: 7.8 | C3: 3.3 | D3: https://www.pes.spb.ru/ | E3: https://www.atsenergo.ru/ | F3: seed_verify_source | G3: Retail tariff: verify with regional supplier/regulator. Export price: verify through ATS market-price data used for microgeneration surplus purchase.
A4: Krasnodar starter | B4: 7.2 | C4: 3.2 | D4: https://kuban.tns-e.ru/ | E4: https://www.atsenergo.ru/ | F4: seed_verify_source | G4: Retail tariff: verify with regional supplier/regulator. Export price: verify through ATS market-price data used for microgeneration surplus purchase.
A5: Rostov-on-Don starter | B5: 7.3 | C5: 3.2 | D5: https://rostov.tns-e.ru/ | E5: https://www.atsenergo.ru/ | F5: seed_verify_source | G5: Retail tariff: verify with regional supplier/regulator. Export price: verify through ATS market-price data used for microgeneration surplus purchase.
A6: Yekaterinburg starter | B6: 7 | C6: 3.1 | D6: https://ekb.esplus.ru/ | E6: https://www.atsenergo.ru/ | F6: seed_verify_source | G6: Retail tariff: verify with regional supplier/regulator. Export price: verify through ATS market-price data used for microgeneration surplus purchase.

Sheet Compatibility
A1: Матрица совместимости (Compatibility Matrix) | B1: Статус (Status) | C1: Причина (Reason) | D1: Источник (Source)
A2: Выбранный инвертор (Selected inverter) | B2: =Inputs!B3 | D2: Inputs
A3: Выбранная панель (Selected panel) | B3: =Inputs!B4 | D3: Inputs
A4: Выбранная АКБ (Selected battery) | B4: =Inputs!B9 | D4: Inputs
A5: Напряжение/ток PV (PV voltage/current) | B5: =Results!B25 | C5: =IF(B5="PASS","PV voltage/current checks pass","PV voltage/current check failed") | D5: Results
A6: Совместимость АКБ (Battery compatibility) | B6: =IF(ISNUMBER(SEARCH("Deye",Results!B30)),"PASS",IF(ISNUMBER(SEARCH("compatible",Results!B30)),"VERIFY","VERIFY")) | C6: =Results!B30 | D6: Batteries
A7: Полнота данных (Data completeness) | B7: =IF(OR(INDEX(Inverters!Q:Q,MATCH(B2,Inverters!C:C,0))="model_only_needs_datasheet",INDEX(Panels!O:O,MATCH(B3,Panels!C:C,0))="model_only_needs_datasheet",INDEX(Batteries!N:N,MATCH(B4,Batteries!C:C,0))="model_only_needs_datasheet"),"VERIFY","PASS") | C7: =IF(B7="VERIFY","One or more selected records need datasheet parameters","Selected records have starter or verified data") | D7: Databases
A8: Общая совместимость (Overall compatibility) | B8: =IF(B5="FAIL","FAIL",IF(OR(B6="VERIFY",B7="VERIFY"),"VERIFY","PASS")) | C8: =IF(B8="PASS","Selected system is preliminarily compatible",IF(B8="FAIL","Selected system fails at least one electrical check","Selected system needs datasheet verification")) | D8: Сводный результат (Combined result)
A10: Проверка (Check) | B10: Статус (Status) | C10: Причина (Reason) | D10: Следующее действие (Next action)
A11: Холодный Voc против max PV voltage (Cold Voc vs max PV voltage) | B11: =Results!B23 | C11: =IF(B11="PASS","Cold string Voc is below inverter max PV voltage","Cold string Voc exceeds inverter max PV voltage") | D11: Изменить панели в строке или инвертор (Adjust panels per string or inverter)
A12: Горячий Vmp против диапазона MPPT (Hot Vmp vs MPPT range) | B12: =Results!B22 | C12: =IF(B12="PASS","Hot string Vmp is inside MPPT range","Hot string Vmp is outside MPPT range") | D12: Изменить панели в строке (Adjust panels per string)
A13: Ток панели против тока MPPT (Panel current vs MPPT current) | B13: =Results!B24 | C13: =IF(B13="PASS","Panel current is within MPPT current limit","Panel current exceeds MPPT current limit") | D13: Изменить строки на MPPT или инвертор (Adjust strings per MPPT or inverter)
A14: Протокол АКБ (Battery protocol) | B14: =B6 | C14: =Results!B30 | D14: Проверить настройки CAN/RS485 (Verify CAN/RS485 settings)
A15: Требуемые данные datasheet (Required datasheet data) | B15: =B7 | C15: =C7 | D15: Заполнить недостающие поля базы (Fill missing database fields)
